Workbook
Name Slicer_Company_Name: #N/A
Name Slicer_Year: #N/A

Sheet Sources
A1: Sources and Bases of the DATA / Assumptions used in the Valuation
A3: S. No | B3: Details of Assumptions/Data Point | C3: Assumed Figure | D3: Remarks | E3: URL
A4: 1 | B4: Actual Financial Statement data for last 7 years | D4: Financial statements has been taken for the last seven years from capitaline database | E4: https://awsone.capitaline.com/index.html#/Company/Condensed/condensed?section=ProfitLoss
A5: 2 | B5: Revenue Growth | C5: 0.08
A6: 3 | B6: Tax Rate | C6: 0.2362 | D6: Cipla Annual Report 2025
A7: 4 | B7: Risk free Rate (Rf) | C7: 0.0667 | D7: 10-year Indian Government bond yield used as proxy for risk-free rate | E7: https://in.investing.com/rates-bonds/india-10-year-bond-yield-historical-data?utm_source
A8: 5 | B8: Market Risk (Rm) | C8: 0.1276313 | D8: Average long-term return of Indian stock market (NIFTY 50) used as market return
B9: Market Risk Premium (Rp= Rm-Rf) | C9: =C8-C7 -> 0.060931297 | D9: Market risk premium calculated as difference between market return and risk-free rate
A10: 6 | B10: Terminal Growth Rate | C10: 0.06 | D10: Terminal growth rate assumed based on long-term GDP growth and pharmaceutical industry growth | E10: https://data.worldbank.org/indicator/NY.GDP.MKTP.KD.ZG
A11: 7 | B11: Cipla Stock Data | D11: Historical stock price data used for Beta calculation | E11: https://www.bseindia.com/
A12: 8 | B12: NIFTY 50 data | D12: Market index data used for Beta calculation | E12: https://www.bseindia.com/
A13: 9 | B13: Current Market Price | C13: 1242.65 | D13: Latest market price from stock exchange | E13: https://awsone.capitaline.com/index.html#/Company/General/CompanyInfo

Sheet Company Overview
A1: CIPLA Limited.
A4: ABOUT THE COMPANY | D4: Segment
A5: Company Name | B5: Cipla Limited | D5: Segment | E5: Key Brands / Therapies | F5: Business Description
A6: Listing | B6: NSE / BSE | D6: Pharmaceuticals (India) | E6: Ciprobay, Asthalin, Foracort, Nexito, Ciplox, Rescof | F6: Branded prescription generics, trade generics, and consumer health products. Largest revenue segment; #3 in Indian Rx market. #1 in Respiratory therapy.
A7: Sector | B7: Healthcare | D7: North America (US) | E7: Generic inhalers, Albuterol, Revlimid (generic), Absorica | F7: Complex generics, inhalation products, and specialty pharma for the US market. Fastest-growing generic player; FY25 revenue of $934 million.
A8: Industry | B8: Pharmaceuticals & Generics | D8: South Africa / Emerging Markets | E8: Cipla Medpro, Cipla Quality Chemical Industries (CQCI) | F8: OTC, branded generics, and tender business. #3 private Rx market in South Africa. Strong presence in Africa and EMEU (Emerging Markets & Europe).
A9: Founded | B9: 1935 | D9: APIs (Active Pharm. Ingredients) | E9: Bulk APIs supplied to third parties and captive use | F9: Manufacture and supply of APIs globally. Supports cost control and supply chain integrity. India is the world's 3rd largest API producer.
A10: Headquarters | B10: Mumbai, India | D10: New Ventures / Digital Health | E10: Wellthy Therapeutics, Digital Breathe Free, Inzpera | F10: Digital therapeutics, telehealth, biosimilars, and specialty pipeline investments. Expansion into obesity (Semaglutide) and inhaled insulin (Afrezza).
A11: Promoter | B11: Hamied Family
A12: Market Cap | B12: Rs. 1.0 Trillion | D12: Growth Drivers – Cipla Limited
D13: Growth Driver | E13: Explanation | F13: Valuation Significance
A14: Cipla Limited represents a structurally strong play on India's branded generics and global respiratory franchise. Its #1 position in respiratory therapy, fast-growing US complex generics portfolio, and expanding South Africa/EMEU presence support durable revenue visibility. The company's investment in digital health and biosimilars provides future growth optionality. However, profitability is sensitive to US generic pricing, regulatory observations, and NPPA pricing controls in India. | D14: Respiratory Market Leadership | E14: Cipla holds #1 rank in India's respiratory therapy. Chronic COPD/asthma burden rising; inhalation CAGR ~9% to 2031. | F14: Supports pricing power, high-margin revenue mix, and competitive moat in complex device-led generics.
D15: US Complex Generics Scale-Up | E15: FY25 US revenue reached $934M (highest ever). Pipeline of injectables, inhalation, and specialty products. | F15: Drives earnings growth and margin expansion; $10B+ patent cliff opportunity by 2029.
D16: Premiumization in India Rx | E16: Chronic share rising (60%+ of India portfolio). Branded prescription growing ~12% YoY with price+mix uplift. | F16: Improves revenue quality and EBITDA margins; reduces cyclicality.
D17: Africa & EMEU Expansion | E17: South Africa private market growing 15-19% YoY; Africa provides tender + OTC revenue diversification. | F17: Adds geographic diversification; CQCI Africa is a long-term structural opportunity.
D18: Biosimilars & New Modalities | E18: Pipeline in semaglutide (GLP-1), oligonucleotides, inhaled insulin (Afrezza); digital therapeutics. | F18: Future growth optionality with high-barrier, high-margin pipeline.
D19: Jan Aushadhi / Trade Generics | E19: Government push for affordable medicines expands volume market; Cipla's trade generics growing double-digit. | F19: Volume growth buffer and rural market penetration.
D20: Omni-Channel & Digital Health | E20: Digital Breathe Free platform (5L+ downloads). E-pharmacy and telehealth integration. | F20: Expands addressable patient base; improves adherence and brand recall.
D21: Brand Equity & Regulatory Track Record | E21: 85%+ of physicians prescribe at least one Cipla product; 47 global manufacturing sites. | F21: Creates durable competitive advantages; supports entry into regulated markets like the US, EU.
D23: Economic Moat – Cipla Limited
A24: Economic Moat – Cipla Limited
A25: Cipla Limited possesses a strong economic moat anchored in three pillars: (1) Device-led inhalation leadership – Cipla's Rotahaler and respiratory franchise is the #1 in India and difficult to replicate, requiring device expertise alongside drug formulation. (2) Regulatory depth – with 47 manufacturing sites, US FDA approvals, and WHO GMP compliance, Cipla has built significant regulatory capital that serves as a durable entry barrier. (3) Brand trust in India and Africa – Cipla's 90-year legacy and Hamied family mission of affordable medicines has created deep physician loyalty (85%+ HCP coverage) and consumer trust. The company's net cash position of ~Rs. 10,369 crore (FY25) provides financial resilience and capacity for bolt-on acquisitions. Tata-like brand recall and public health credibility further reinforce competitive durability.

Sheet Industry Overview
B1: Industry Analysis – Key Insights
B2: Cipla Revenue Trend | C2: Cipla's consolidated revenue has grown from ~Rs. 9,774 Cr (FY15) to ~Rs. 28,400 Cr (FY25), representing a ~11% CAGR over a decade. Growth has been driven by three engines: India branded prescription (+10-12% annually), North America complex generics (now $934M annually), and South Africa/EMEU markets. The company crossed Rs. 25,000 Cr in FY24 – a milestone that confirms large-cap generics scale. Revenue quality has improved as Cipla's revenue mix shifts toward complex, high-margin products (inhalers, specialty generics, biosimilars).
B4: India Pharma Market & Organized Share | C4: India's pharma market grew from $20 Bn to $42 Bn over 2015-2025. Crucially, the organized segment's share has expanded from ~45% to ~60%, benefiting branded generics players like Cipla. Government schemes (Ayushman Bharat, PM Jan Aushadhi) have widened access while also constraining NPPA-regulated pricing. Cipla's India market share (~5.7%) has remained stable, reflecting both competitive market dynamics and Cipla's consistent outperformance in respiratory therapy.
B6: US Market & Complex Generics | C6: North America revenue has scaled from ~$320M (FY15) to $934M (FY25), driven by complex generic launches (Albuterol, Revlimid, specialty injectables). The US generic market faces structural pricing erosion in plain generics, but complex products (inhalers, injectables, modified-release) provide pricing stability. Cipla is positioned as a 'fastest-growing generic player' in the US. The upcoming $10B+ patent cliff (2026-29) offers incremental launch opportunities.
B8: Respiratory Market Leadership | C8: Cipla's respiratory franchise is its deepest moat. India's respiratory burden (37M+ asthma/COPD patients) and rising pollution-linked cases (274 days exceeding WHO limits in Delhi) structurally support double-digit inhaler market growth. Cipla's Rotahaler platform and Foracort brand franchise dominate. Globally, inhalation therapy markets are expanding at 9%+ CAGR, and Cipla's device expertise creates high barriers for new entrants – regulatory ANDA pathways for inhalers are complex and time-consuming.
B10: Across the study period, Cipla's industry positioning has strengthened materially. The company has successfully navigated the complexity of operating across four distinct markets (India, US, South Africa, EMEU) with differentiated product strategies in each. The shift toward complex generics, inhalation, and specialty pharma has improved revenue quality and margin resilience. Market share in India's organized sector has remained stable while organized sector share itself expands – a structural tailwind. The industry's long-term outlook is favorable: India projected to reach $120-130 Bn by 2030, global patent cliff of $10B+ by 2029, and biosimilar/GLP-1 new market creation. Collectively, Cipla's industry analysis supports durable mid-to-high single digit revenue growth with margin expansion driven by complex product mix.
A17: Year | B17: India Pharma Mkt (USD Bn) | C17: Cipla Revenue (Rs Cr) | D17: Cipla US Revenue (USD Mn) | E17: Organized Generics Share (%) | F17: Cipla India Mkt Share (%) | G17: Respiratory Market (Rs Cr)
A18: 2015 | B18: 20 | C18: 9774 | D18: 320 | E18: 45 | F18: 4.8 | G18: 8000 | I18: Over the period 2015 to 2025, the Indian pharmaceutical market shows strong expansion, growing from $20 billion to $42 billion, indicating a robust increase in healthcare demand and industry potential. Alongside this, Cipla demonstrates consistent and significant revenue growth, with its revenue rising from ₹9,774 crore to ₹28,400 crore, reflecting strong operational performance and market positioning. A key contributor to this growth is the company’s increasing presence in the US market, where revenue nearly tripled from $320 million to $934 million, highlighting its success in regulated and high-margin markets. The share of organized generics also increased from 45% to 60%, suggesting a structural shift in the industry that benefits established players like Cipla. Although Cipla’s India market share improved from 4.8% to 5.8%, the growth remains gradual, indicating intense competition in the domestic market. Additionally, the respiratory segment, which is Cipla’s core strength, expanded significantly from ₹8,000 crore to ₹21,000 crore, supporting its competitive advantage. Overall, the data reflects that Cipla is on a strong growth trajectory driven by global expansion and therapeutic specialization, while still facing competitive pressures in its home market.
A19: 2016 | B19: 21.5 | C19: 10938 | D19: 360 | E19: 47 | F19: 5 | G19: 8800
A20: 2017 | B20: 23 | C20: 12055 | D20: 380 | E20: 48 | F20: 5.1 | G20: 9500
A21: 2018 | B21: 25 | C21: 14273 | D21: 390 | E21: 50 | F21: 5.2 | G21: 10500
A22: 2019 | B22: 27 | C22: 16363 | D22: 400 | E22: 51 | F22: 5.3 | G22: 11500
A23: 2020 | B23: 24 | C23: 16779 | D23: 420 | E23: 52 | F23: 5.5 | G23: 13000
A24: 2021 | B24: 26.5 | C24: 19160 | D24: 520 | E24: 54 | F24: 5.6 | G24: 14500
A25: 2022 | B25: 30 | C25: 20038 | D25: 620 | E25: 56 | F25: 5.5 | G25: 16000
A26: 2023 | B26: 33 | C26: 22753 | D26: 720 | E26: 57 | F26: 5.6 | G26: 17500
A27: 2024 | B27: 38 | C27: 25774 | D27: 830 | E27: 58 | F27: 5.7 | G27: 19000
A28: 2025 | B28: 42 | C28: 28400 | D28: 934 | E28: 60 | F28: 5.8 | G28: 21000
A31: Year | B31: Cipla Rev Growth (%) | C31: India Pharma Mkt Growth (%) | D31: US Rev Growth (%) | E31: Org. Share Change (pp) | F31: Resp Mkt Growth (%)
A32: 2015 | B32: - | C32: - | D32: - | E32: - | F32: -
A33: 2016 | B33: 12 | C33: 7.5 | D33: 12.5 | E33: 2 | F33: 10
A34: 2017 | B34: 10 | C34: 7 | D34: 5.6 | E34: 1 | F34: 8
A35: 2018 | B35: 18 | C35: 8.7 | D35: 2.6 | E35: 2 | F35: 10.5
A36: 2019 | B36: 15 | C36: 8 | D36: 2.6 | E36: 1 | F36: 9.5
A37: 2020 | B37: 2 | C37: -11.1 | D37: 5 | E37: 1 | F37: 13
A38: 2021 | B38: 14 | C38: 10.4 | D38: 23.8 | E38: 2 | F38: 11.5
A39: 2022 | B39: 5 | C39: 13.2 | D39: 19.2 | E39: 2 | F39: 10.3
A40: 2023 | B40: 14 | C40: 10 | D40: 16.1 | E40: 1 | F40: 9.4
A41: 2024 | B41: 13 | C41: 15.2 | D41: 15.3 | E41: 1 | F41: 8.6
A42: 2025 | B42: 10 | C42: 10.5 | D42: 12.5 | E42: 2 | F42: 10.5

Sheet Raw Data
A1: CIPLA LIMITED – INCOME STATEMENT (Source: Capitaline) | J1: CIPLA LIMITED – BALANCE SHEET (Source: Capitaline)
A2: Particulars (INR Cr.) | B2: 2019 | C2: 2020 | D2: 2021 | E2: 2022 | F2: 2023 | G2: 2024 | H2: 2025 | J2: Particulars (INR Cr.) | K2: 2019 | L2: 2020 | M2: 2021 | N2: 2022 | O2: 2023 | P2: 2024 | Q2: 2025
A3: INCOME STATEMENT | J3: BALANCE SHEET
A5: Year | B5: 2019 | C5: 2020 | D5: 2021 | E5: 2022 | F5: 2023 | G5: 2024 | H5: 2025 | J5: Year | K5: 2019 | L5: 2020 | M5: 2021 | N5: 2022 | O5: 2023 | P5: 2024 | Q5: 2025
A6: INCOME : | J6: Shareholder's Funds
A7: Sales Turnover | B7: 12374.01 | C7: 12659.15 | D7: 11302.71 | E7: 13091.79 | F7: 14345.34 | G7: 16574.34 | H7: 19044.85 | J7: Share Capital | K7: 161.14 | L7: 161.25 | M7: 161.29 | N7: 161.36 | O7: 161.43 | P7: 161.47 | Q7: 161.52
A8: Net Sales | B8: 12374.01 | C8: 12659.15 | D8: 11302.71 | E8: 13091.79 | F8: 14345.34 | G8: 16574.34 | H8: 19044.85 | J8: Ordinary Capital | K8: 161.14 | L8: 161.25 | M8: 161.29 | N8: 161.36 | O8: 161.43 | P8: 161.47 | Q8: 161.52
A9: Other Income | B9: 577.52 | C9: 892.85 | D9: 653.91 | E9: 935.24 | F9: 826.2 | G9: 1433.72 | H9: 1279.38 | J9: Reserves and Surplus | K9: 15620.77 | L9: 17241.71 | M9: 19766.27 | N9: 22352.19 | O9: 24476.66 | P9: 27812.45 | Q9: 31937.72
A10: Dividend Income | B10: 241.5 | C10: 565.51 | D10: 0 | E10: 403.32 | F10: 14.92 | G10: 380.69 | H10: 99.27 | J10: Total Shareholder's Fund | K10: 15781.91 | L10: 17402.96 | M10: 19927.56 | N10: 22513.55 | O10: 24638.09 | P10: 27973.92 | Q10: 32099.24
A11: Interest Income | B11: 59.63 | C11: 60.91 | D11: 36.42 | E11: 72.89 | F11: 158.74 | G11: 293.82 | H11: 399.65 | J11: Non-Current Liabilities
A12: Profit on sale of Fixed Assets | B12: 0 | C12: 2.86 | D12: 3.48 | E12: 0.72 | F12: 11.02 | G12: 7.5 | H12: -1.85 | J12: Long-Term Borrowings | K12: 0 | L12: 0 | M12: 0 | N12: 0 | O12: 0 | P12: 0 | Q12: 0
A13: Profit on sale of investments | B13: 107.41 | C13: 114.02 | D13: 47.67 | E13: 64 | F13: 118.13 | G13: 43.47 | H13: 143.13 | J13: Lease Liabilities | K13: 0 | L13: 0 | M13: 29.46 | N13: 15.53 | O13: 35.53 | P13: 29.55 | Q13: 86.18
A14: Rent received | B14: 5.35 | C14: 9.16 | D14: 15.91 | E14: 12.6 | F14: 9.11 | G14: 14.16 | H14: 15.73 | J14: Deferred Tax Liabilities (Net) | K14: 42.84 | L14: 112.97 | M14: 104.91 | N14: 79.25 | O14: 36.13 | P14: 32.64 | Q14: 0
A15: Gain on Cancell. of Forward Contr/forex trans | B15: 20.38 | C15: 119.39 | D15: 44.13 | E15: 65.77 | F15: 92.59 | G15: 46.2 | H15: 5.6 | J15: Deferred Tax Liability | K15: 494.77 | L15: 353.62 | M15: 104.91 | N15: 313.69 | O15: 286.08 | P15: 243.71 | Q15: 0
A16: Refunds / Claims Received | B16: 4.58 | C16: 2.99 | D16: 1.38 | E16: 8.58 | F16: 16.84 | G16: 4.6 | H16: 14.52 | J16: Deferred Tax Assets | K16: 451.93 | L16: 240.65 | M16: 0 | N16: 234.44 | O16: 249.95 | P16: 211.07 | Q16: 0
A17: Income from Subsidiaries | B17: 0 | C17: 0.07 | D17: 0 | E17: 0 | F17: 0 | G17: 4.93 | H17: 0 | J17: Other Long Term Liabilities | K17: 117.86 | L17: 165.3 | M17: 113.9 | N17: 99.75 | O17: 105.25 | P17: 60.63 | Q17: 87.76
A18: Income from Investment Activities | B18: 19.11 | C18: -20.91 | D18: 10.12 | E18: 3.23 | F18: 13.89 | G18: 215.01 | H18: 237.02 | J18: Long-Term Provisions | K18: 108.12 | L18: 105.14 | M18: 95.97 | N18: 81.63 | O18: 81.73 | P18: 94.24 | Q18: 109.12
A19: Provision Written Back | B19: 19.11 | C19: 2.41 | D19: 0 | E19: 0 | F19: 0 | G19: 7.03 | H19: 5.5 | J19: Total Non Current Liabilities | K19: 268.82 | L19: 383.41 | M19: 344.24 | N19: 276.16 | O19: 258.64 | P19: 217.06 | Q19: 283.06
A20: Miscellaneous Income | B20: 19.11 | C20: 36.44 | D20: 494.8 | E20: 304.13 | F20: 390.96 | G20: 416.31 | H20: 360.81 | J20: Current Liabilities
A21: Stock Adjustments | B21: 19.11 | C21: 43.08 | D21: -6.41 | E21: 528.4 | F21: -194.32 | G21: -104.57 | H21: 229.87 | J21: Short-Term Borrowings | K21: 0 | L21: 6.06 | M21: 0 | N21: 0 | O21: 0 | P21: 0 | Q21: 0
A22: Total Income | B22: 19.11 | C22: 13595.08 | D22: 11950.21 | E22: 14555.43 | F22: 14977.22 | G22: 17903.49 | H22: 20554.1 | J22: Lease Liabilities | L22: 0 | M22: 29.46 | N22: 15.53 | O22: 35.53 | P22: 29.55 | Q22: 86.18
A23: EXPENDITURE : | J23: Trade Payables | K23: 1481.35 | L23: 1612.12 | M23: 1495.49 | N23: 1569.73 | O23: 1638.92 | P23: 1684.64 | Q23: 1883.71
A24: Raw Materials | B24: 4371.46 | C24: 4362.29 | D24: 4097.2 | E24: 5618.64 | F24: 4739.89 | G24: 4977.62 | H24: 5699.59 | J24: Other Current Liabilities | K24: 406.59 | L24: 455.04 | M24: 548.66 | N24: 450.3 | O24: 399.52 | P24: 407.08 | Q24: 435.65
A25: Opening Stock of Raw Materials | B25: 1285.05 | C25: 1245.28 | D25: 1349.14 | E25: 1395.51 | F25: 1268.82 | G25: 1205.94 | H25: 1281.48 | J25: Short-Term Provisions | K25: 480.14 | L25: 546.07 | M25: 625.13 | N25: 631.39 | O25: 646.74 | P25: 754.53 | Q25: 832.86
A26: Purchases of Raw Material | B26: 3072.48 | C26: 3103.03 | D26: 2056.32 | E26: 1886.11 | F26: 3512.68 | G26: 3441.97 | H26: 3740.56 | J26: Total Current Liabilities | K26: 2368.08 | L26: 2619.29 | M26: 2691.94 | N26: 2659.34 | O26: 2699.74 | P26: 2862.25 | Q26: 3183.42
A27: Purchase of Trading Goods | B27: 1259.21 | C27: 1363.12 | D27: 1847.85 | E27: 2850.85 | F27: 1993.39 | G27: 2360.41 | H27: 2056.75 | J27: Other Equity & Liabilities | K27: 0 | L27: 0 | M27: 0 | N27: 0 | O27: 0 | P27: 0 | Q27: 0
A28: Closing Stock of Raw Materials | B28: 1245.28 | C28: 1349.14 | D28: 1395.51 | E28: 1065.76 | F28: 1205.94 | G28: 1281.48 | H28: 1379.2 | J28: TOTAL EQUITY AND LIABILITIES | K28: 18418.81 | L28: 20405.66 | M28: 22963.74 | N28: 25449.05 | O28: 27596.47 | P28: 31053.23 | Q28: 35565.72
A29: Adjustment on amalgamation / trial runs | B29: 0 | C29: 0 | D29: 239.4 | E29: 551.93 | F29: -829.06 | G29: -749.22 | H29: 0 | J29: Non-Current Assets
A30: Power & Fuel Cost | B30: 264.93 | C30: 253.95 | D30: 234.58 | E30: 247.58 | F30: 257.07 | G30: 271.66 | H30: 290.24 | J30: Fixed Assets | K30: 4424.79 | L30: 4344.27 | M30: 4297.77 | N30: 4114.25 | O30: 4251.53 | P30: 4273.41 | Q30: 4403.16
A31: Power, Oil & Fuel | B31: 264.93 | C31: 253.95 | D31: 234.58 | E31: 247.58 | F31: 257.07 | G31: 271.66 | H31: 290.24 | J31: Tangible Assets | K31: 3992.13 | L31: 3686.18 | M31: 3569.27 | N31: 3554.91 | O31: 3449.67 | P31: 3278.31 | Q31: 3347.53
A32: Employee Cost | B32: 1839.84 | C32: 1911.08 | D32: 1703.58 | E32: 1729.16 | F32: 2380.68 | G32: 2688.51 | H32: 3054.87 | J32: Intangible Assets | K32: 135.33 | L32: 205.87 | M32: 269.51 | N32: 215.96 | O32: 199.45 | P32: 232.75 | Q32: 257.12
A33: Salaries,Wages & Bonus | B33: 1633.63 | C33: 1724 | D33: 1835.46 | E33: 1914.9 | F33: 2132.71 | G33: 2418.16 | H33: 2722.23 | J33: Capital Work-in-Progress | K33: 241.32 | L33: 255.73 | M33: 275.04 | N33: 186.26 | O33: 441.53 | P33: 580.9 | Q33: 523.11
A34: Contribution to funds | B34: 98 | C34: 96.77 | D34: 95.13 | E34: 90.65 | F34: 93.51 | G34: 101.46 | H34: 127.02 | J34: Intangible assets under development | K34: 56.01 | L34: 64 | M34: 80.07 | N34: 81.42 | O34: 62.72 | P34: 89.37 | Q34: 115.29
A35: Staff Welfare Expenses | B35: 86.2 | C35: 71.75 | D35: 93.51 | E35: 96.78 | F35: 130.99 | G35: 143.82 | H35: 178.47 | J35: Right-of-Use Assets | L35: 132.49 | M35: 103.88 | N35: 75.7 | O35: 98.16 | P35: 92.08 | Q35: 160.11
A36: Other Employee Cost | B36: 22.01 | C36: 18.56 | D36: -320.52 | E36: -373.17 | F36: 23.47 | G36: 25.07 | H36: 27.15 | J36: Non-Current Investments | K36: 3865.46 | L36: 6481.76 | M36: 7844.78 | N36: 8998.23 | O36: 9199.63 | P36: 9525.66 | Q36: 10614.55
A37: Other Manufacturing Expenses | B37: 861.96 | C37: 921.04 | D37: 906.09 | E37: 994.55 | F37: 988.99 | G37: 1243.47 | H37: 1374.94 | J37: Deferred Tax Assets (net) | K37: 0 | L37: 0 | M37: 0 | N37: 0 | O37: 0 | P37: 0 | Q37: 19.88
A38: Job Work / Contract / Processing Charges | B38: 158.93 | C38: 178.38 | D38: 189.43 | E38: 180.11 | F38: 207.56 | G38: 241.35 | H38: 269.03 | J38: Deferred Tax Assets | K38: 451.93 | L38: 240.65 | M38: 0 | N38: 234.44 | O38: 249.95 | P38: 211.07 | Q38: 0
A39: Stores Consumed | B39: 100.49 | C39: 120.33 | D39: 98.18 | E39: 107.94 | F39: 103.85 | G39: 110.49 | H39: 132.58 | J39: Deferred Tax Liability | K39: 494.77 | L39: 353.62 | M39: 104.91 | N39: 313.69 | O39: 286.08 | P39: 243.71 | Q39: 0
A40: Repairs | B40: 108.8 | C40: 120.62 | D40: 119.41 | E40: 145.81 | F40: 156.53 | G40: 159.94 | H40: 178.27 | J40: Long-Term Loans and Advances | K40: 609.23 | L40: 539.32 | M40: 615.26 | N40: 555.68 | O40: 748.77 | P40: 1904.67 | Q40: 1735.25
A41: Repairs - Plant & machinery | B41: 78.42 | C41: 93.46 | D41: 93.91 | E41: 115.29 | F41: 123.56 | G41: 127.59 | H41: 148.22 | J41: Other Non-Current Assets | K41: 40.68 | L41: 13.25 | M41: 13.75 | N41: 346.98 | O41: 25.41 | P41: 442.69 | Q41: 384.11
A42: Repairs - Building | B42: 30.38 | C42: 27.16 | D42: 25.5 | E42: 30.52 | F42: 32.97 | G42: 32.35 | H42: 30.05 | J42: Total Non Current Assets | K42: 8940.16 | L42: 11378.6 | M42: 12771.56 | N42: 14015.14 | O42: 14225.34 | P42: 16146.43 | Q42: 17156.95
A43: Other Operating Expenses | B43: 493.74 | C43: 501.71 | D43: 499.07 | E43: 560.69 | F43: 521.05 | G43: 731.69 | H43: 795.06 | J43: Current Assets
A44: Selling and Administration Expenses | B44: 2030.01 | C44: 2093.92 | D44: 1578.59 | E44: 2107.17 | F44: 2334.97 | G44: 2510.53 | H44: 2604.73 | J44: Current Investments | K44: 2011.58 | L44: 834.43 | M44: 2004.84 | N44: 2038.8 | O44: 2771.44 | P44: 4383.59 | Q44: 6849.31
A45: Rent,Rates and Taxes paid | B45: 85.76 | C45: 69.42 | D45: 89.28 | E45: 115.32 | F45: 123.93 | G45: 126.95 | H45: 123.19 | J45: Inventories | K45: 2868.41 | L45: 3021.36 | M45: 3085.81 | N45: 3485.81 | O45: 3277.36 | P45: 3254.28 | Q45: 3607.12
A46: Others | B46: 85.76 | C46: 69.42 | D46: 89.28 | E46: 115.32 | F46: 123.93 | G46: 126.95 | H46: 123.19 | J46: Trade Receivables | K46: 3168.73 | L46: 3560.27 | M46: 3035.37 | N46: 2794.48 | O46: 2888.49 | P46: 2681.75 | Q46: 3859.99
A47: Insurance | B47: 16.2 | C47: 28.58 | D47: 38.99 | E47: 46.64 | F47: 50.44 | G47: 48.34 | H47: 48.8 | J47: Cash and Cash Equivalents | K47: 174.56 | L47: 523.07 | M47: 874.8 | N47: 1428.03 | O47: 966.46 | P47: 333.2 | Q47: 278.45
A48: Distribution Expenses | B48: 170.6 | C48: 159.7 | D48: 208.19 | E48: 247.19 | F48: 232.6 | G48: 285.89 | H48: 372.73 | J48: Short-Term Loans and Advances | K48: 992.7 | L48: 834.5 | M48: 904.65 | N48: 1376.26 | O48: 3143.24 | P48: 3714.46 | Q48: 3349.67
A49: Other Selling Expenses | B49: 363.66 | C49: 321.49 | D49: 289.98 | E49: 411.51 | F49: 426.09 | G49: 411.43 | H49: 407.64 | J49: Other Current Assets | K49: 262.67 | L49: 253.43 | M49: 286.71 | N49: 211.66 | O49: 324.14 | P49: 490.56 | Q49: 424.68
A50: Legal Expenses | B50: 425.94 | C50: 557.13 | D50: 471.88 | E50: 542.9 | F50: 594.09 | G50: 676.07 | H50: 800.5 | J50: Total Current Assets | K50: 9478.65 | L50: 9027.06 | M50: 10192.18 | N50: 11335.04 | O50: 13371.13 | P50: 14857.84 | Q50: 18369.22
A51: Communication Expenses | B51: 30.37 | C51: 19.29 | D51: 18.37 | E51: 20.22 | F51: 24.27 | G51: 25.59 | H51: 31.51 | J51: Other Assets | K51: 0 | L51: 0 | M51: 0 | N51: 98.87 | O51: 0 | P51: 48.96 | Q51: 39.55
A52: Travel Expenses | B52: 275.1 | C52: 315.86 | D52: 84.95 | E52: 157.4 | F52: 234.25 | G52: 317.37 | H52: 349 | J52: TOTAL ASSETS | K52: 18418.81 | L52: 20405.66 | M52: 22963.74 | N52: 25449.05 | O52: 27596.47 | P52: 31053.23 | Q52: 35565.72
A53: Audit Expenses | B53: 1.91 | C53: 2.19 | D53: 2.75 | E53: 2.94 | F53: 3.32 | G53: 3.14 | H53: 3.81
A54: Director''s Remuneration | B54: 9.12 | C54: 8.57 | D54: 8.64 | E54: 10.95 | F54: 10.99 | G54: 14.31 | H54: 18.51
A55: Other Commission paid | B55: 270.12 | C55: 220.18 | D55: 180.49 | E55: 248.7 | F55: 231.39 | G55: 197.22 | H55: 84.06
A56: R & D Expenses | B56: 381.23 | C56: 391.51 | D56: 185.07 | E56: 303.4 | F56: 403.6 | G56: 404.22 | H56: 364.98
A57: Miscellaneous Expenses | B57: 367.11 | C57: 452.66 | D57: -291.15 | E57: -443.38 | F57: 282.43 | G57: 293.83 | H57: 471.91
A58: Donations | B58: 11.99 | C58: 17.14 | D58: 1.9 | E58: 3.54 | F58: 24.35 | G58: 40.4 | H58: 0.36
A59: Loss on Sale of Assets | B59: 2.93 | C59: 0 | D59: 0 | E59: 0 | F59: 0 | G59: 0 | H59: 0
A60: Bad Debts written off | B60: 42.88 | C60: 103.5 | D60: 19.65 | E60: 14.19 | F60: 0 | G60: 0 | H60: 0
A61: Provision for doubtful loan/ Deposit/ Advances | B61: 0 | C61: 0 | D61: 0 | E61: 0 | F61: -7.78 | G61: 9.22 | H61: -1.89
A62: Provision/Impairment of Assets | B62: 0 | C62: 0 | D62: 0 | E62: 0 | F62: 185.9 | G62: 0 | H62: 0
A63: Other Miscellaneous Expenses | B63: 275.89 | C63: 295.71 | D63: -355.54 | E63: -514.36 | F63: 17.82 | G63: 174.97 | H63: 393.86
A64: CSR Expenses | B64: 33.42 | C64: 36.31 | D64: 42.84 | E64: 53.25 | F64: 62.14 | G64: 69.24 | H64: 79.58
... A101: Dividend Per Share Adj.(Rs) | B101: 3 | C101: 4 | D101: 5 | E101: 5 | F101: 8.5 | G101: 13 | H101: 16
A105: CIPLA LIMITED – CASH FLOW STATEMENT (Source: Capitaline)
A106: Particulars (INR Cr.) | B106: 2019 | C106: 2020 | D106: 2021 | E106: 2022 | F106: 2023 | G106: 2024 | H106: 2025
A107: Cash at Beginning of Year | B107: 217.45 | C107: 64.47 | D107: 261.54 | E107: 294.72 | F107: 177.29 | G107: 29.48 | H107: 164.52
A108: Net Cash from Operating Activities | B108: 1468.05 | C108: 2018.14 | D108: 3460.31 | E108: 2773.43 | F108: 3035.05 | G108: 3726.77 | H108: 3300.99
A109: Purchase of Fixed Assets (Capex) | B109: -312.05 | C109: -449.71 | D109: -516.97 | E109: -331.68 | F109: -684.15 | G109: -682.71 | H109: -728.68
A110: Net Cash Used in Investing Activities | B110: -1147.71 | C110: -1127.18 | D110: -3361.33 | E110: -2464.14 | F110: -2758.09 | G110: -2882.9 | H110: -2308.84
A111: Net Cash Used in Financing Activities | B111: -473.32 | C111: -693.89 | D111: -65.8 | E111: -426.72 | F111: -424.77 | G111: -708.83 | H111: -1073.93
A112: Net Inc/(Dec) in Cash & Cash Equiv | B112: -152.98 | C112: 197.07 | D112: 33.18 | E112: -117.43 | F112: -147.81 | G112: 135.04 | H112: -81.78
A113: Cash at End of Year | B113: 64.47 | C113: 261.54 | D113: 294.72 | E113: 177.29 | F113: 29.48 | G113: 164.52 | H113: 82.74

Sheet CF Assumptions
B1: CIPLA LIMITED – CASH FLOW STATEMENT (PROJECTED)
B2: INR in Crores | Actual FY2019–FY2025 from Raw Data | Forecast FY2026–FY2030 from Financial Statements & PPE Schedule
B4: Particulars | C4: 2019 Actual | D4: 2020 Actual | E4: 2021 Actual | F4: 2022 Actual | G4: 2023 Actual | H4: 2024 Actual | I4: 2025 Actual | J4: 2026 Forecast | K4: 2027 Forecast | L4: 2028 Forecast | M4: 2029 Forecast | N4: 2030 Forecast
B5: Cash at Beginning of Year | C5: ='Raw Data'!B107 -> 217.45 | D5: ='Raw Data'!C107 -> 64.47 | E5: ='Raw Data'!D107 -> 261.54 | F5: ='Raw Data'!E107 -> 294.72 | G5: ='Raw Data'!F107 -> 177.29 | H5: ='Raw Data'!G107 -> 29.48 | I5: ='Raw Data'!H107 -> 164.52 | J5: =I22 -> 82.74 | K5: =J22 -> -2372.6913 | L5: =K22 -> -4161.3044 | M5: =L22 -> -6187.9299 | N5: =M22 -> -8388.8392
B6: OPERATING ACTIVITIES
B7: Net Profit After Tax (PAT) | C7: ='Raw Data'!B77 -> 1888.41 | D7: ='Raw Data'!C77 -> 2318.17 | E7: ='Raw Data'!D77 -> 2468.28 | F7: ='Raw Data'!E77 -> 2957.93 | G7: ='Raw Data'!F77 -> 2513.47 | H7: ='Raw Data'!G77 -> 4077.25 | I7: ='Raw Data'!H77 -> 5157.65 | J7: ='Financial Statements'!J25 -> 1500.2186 | K7: ='Financial Statements'!K25 -> 1673.3212 | L7: ='Financial Statements'!L25 -> 1821.2089 | M7: ='Financial Statements'!M25 -> 2043.3786 | N7: ='Financial Statements'!N25 -> 2533.9679
B8: Add: Depreciation & Amortisation | C8: ='Raw Data'!B71 -> 569.72 | D8: ='Raw Data'!C71 -> 599.78 | E8: ='Raw Data'!D71 -> 468.62 | F8: ='Raw Data'!E71 -> 460.01 | G8: ='Raw Data'!F71 -> 595.91 | H8: ='Raw Data'!G71 -> 587.59 | I8: ='Raw Data'!H71 -> 573.89 | J8: ='Financial Statements'!J17 -> 704.5056 | K8: ='Financial Statements'!K17 -> 713.53092 | L8: ='Financial Statements'!L17 -> 736.83114 | M8: ='Financial Statements'!M17 -> 721.05845 | N8: ='Financial Statements'!N17 -> 761.29694
B9: Add: Finance Cost (Non-Cash Add-Back) | C9: ='Raw Data'!B67 -> 16.97 | D9: ='Raw Data'!C67 -> 36.05 | E9: ='Raw Data'!D67 -> 45.07 | F9: ='Raw Data'!E67 -> 26.93 | G9: ='Raw Data'!F67 -> 22.27 | H9: ='Raw Data'!G67 -> 20.25 | I9: ='Raw Data'!H67 -> 15.11 | J9: ='Financial Statements'!J18 -> 18 | K9: ='Financial Statements'!K18 -> 18 | L9: ='Financial Statements'!L18 -> 20 | M9: ='Financial Statements'!M18 -> 20 | N9: ='Financial Statements'!N18 -> 22
B10: (Inc)/Dec in Inventories | D10: ='Raw Data'!B45-'Raw Data'!C45 -> 16.34 | E10: ='Raw Data'!C45-'Raw Data'!D45 -> -19.86 | F10: ='Raw Data'!D45-'Raw Data'!E45 -> -26.04 | G10: ='Raw Data'!E45-'Raw Data'!F45 -> -8.61 | H10: ='Raw Data'!F45-'Raw Data'!G45 -> -3.02 | I10: ='Raw Data'!G45-'Raw Data'!H45 -> 3.76 | J10: ='Financial Statements'!I62-'Financial Statements'!J62 -> -1164.6432 | K10: ='Financial Statements'!J62-'Financial Statements'!K62 -> -382.32872 | L10: ='Financial Statements'!K62-'Financial Statements'!L62 -> -389.53874 | M10: ='Financial Statements'!L62-'Financial Statements'!M62 -> -288.23571 | N10: ='Financial Statements'!M62-'Financial Statements'!N62 -> -301.9276
B11: (Inc)/Dec in Trade Receivables | D11: ='Raw Data'!B46-'Raw Data'!C46 -> 16.34 | E11: ='Raw Data'!C46-'Raw Data'!D46 -> -19.86 | F11: ='Raw Data'!D46-'Raw Data'!E46 -> -26.04 | G11: ='Raw Data'!E46-'Raw Data'!F46 -> -8.61 | H11: ='Raw Data'!F46-'Raw Data'!G46 -> -3.02 | I11: ='Raw Data'!G46-'Raw Data'!H46 -> 3.76 | J11: ='Financial Statements'!I63-'Financial Statements'!J63 -> -797.76137 | K11: ='Financial Statements'!J63-'Financial Statements'!K63 -> -278.59786 | L11: ='Financial Statements'!K63-'Financial Statements'!L63 -> -192.62234 | M11: ='Financial Statements'!L63-'Financial Statements'!M63 -> -207.60539 | N11: ='Financial Statements'!M63-'Financial Statements'!N63 -> -396.98665
B12: Inc/(Dec) in Trade Payables | D12: ='Raw Data'!C23-'Raw Data'!B23 -> 0 | E12: ='Raw Data'!D23-'Raw Data'!C23 -> 0 | F12: ='Raw Data'!E23-'Raw Data'!D23 -> 0 | G12: ='Raw Data'!F23-'Raw Data'!E23 -> 0 | H12: ='Raw Data'!G23-'Raw Data'!F23 -> 0 | I12: ='Raw Data'!H23-'Raw Data'!G23 -> 0 | J12: ='Financial Statements'!J47-'Financial Statements'!I47 -> 508.32697 | K12: ='Financial Statements'!K47-'Financial Statements'!J47 -> 180.51576 | L12: ='Financial Statements'!L47-'Financial Statements'!K47 -> 166.2532 | M12: ='Financial Statements'!M47-'Financial Statements'!L47 -> 151.91195 | N12: ='Financial Statements'!N47-'Financial Statements'!M47 -> 197.93537
B13: Net Cash from Operating Activities (CFO) | C13: ='Raw Data'!B108 -> 1468.05 | D13: ='Raw Data'!C108 -> 2018.14 | E13: ='Raw Data'!D108 -> 3460.31 | F13: ='Raw Data'!E108 -> 2773.43 | G13: ='Raw Data'!F108 -> 3035.05 | H13: ='Raw Data'!G108 -> 3726.77 | I13: ='Raw Data'!H108 -> 3300.99 | J13: =J7+J8+J9+J10+J11+J12 -> 768.64659 | K13: =K7+K8+K9+K10+K11+K12 -> 1924.4413 | L13: =L7+L8+L9+L10+L11+L12 -> 2162.1322 | M13: =M7+M8+M9+M10+M11+M12 -> 2440.5079 | N13: =N7+N8+N9+N10+N11+N12 -> 2816.286
B14: INVESTING ACTIVITIES
B15: Purchase of Fixed Assets (Capex) – from Cash Flow Statement | C15: ='Raw Data'!B109 -> -312.05 | D15: ='Raw Data'!C109 -> -449.71 | E15: ='Raw Data'!D109 -> -516.97 | F15: ='Raw Data'!E109 -> -331.68 | G15: ='Raw Data'!F109 -> -684.15 | H15: ='Raw Data'!G109 -> -682.71 | I15: ='Raw Data'!H109 -> -728.68 | J15: =-'PPE Schedule'!J8 -> -760.91385 | K15: =-'PPE Schedule'!K8 -> -859.15732 | L15: =-'PPE Schedule'!L8 -> -938.69285 | M15: =-'PPE Schedule'!M8 -> -989.31504 | N15: =-'PPE Schedule'!N8 -> -1119.8186
B16: Other Investing Activities (Investments & Others) | C16: ='Raw Data'!B110-'Raw Data'!B109 -> -835.66 | D16: ='Raw Data'!C110-'Raw Data'!C109 -> -677.47 | E16: ='Raw Data'!D110-'Raw Data'!D109 -> -2844.36 | F16: ='Raw Data'!E110-'Raw Data'!E109 -> -2132.46 | G16: ='Raw Data'!F110-'Raw Data'!F109 -> -2073.94 | H16: ='Raw Data'!G110-'Raw Data'!G109 -> -2200.19 | I16: ='Raw Data'!H110-'Raw Data'!H109 -> -1580.16 | J16: =-('Financial Statements'!J57-'Financial Statements'!I57) -> -849.164 | K16: =-('Financial Statements'!K57-'Financial Statements'!J57) -> -917.09712 | L16: =-('Financial Statements'!L57-'Financial Statements'!K57) -> -990.46489 | M16: =-('Financial Statements'!M57-'Financial Statements'!L57) -> -1069.7021 | N16: =-('Financial Statements'!N57-'Financial Statements'!M57) -> -1155.2782
B17: Net Cash Used in Investing Activities (CFI) | C17: ='Raw Data'!B110 -> -1147.71 | D17: ='Raw Data'!C110 -> -1127.18 | E17: ='Raw Data'!D110 -> -3361.33 | F17: ='Raw Data'!E110 -> -2464.14 | G17: ='Raw Data'!F110 -> -2758.09 | H17: ='Raw Data'!G110 -> -2882.9 | I17: ='Raw Data'!H110 -> -2308.84 | J17: =J15+J16 -> -1610.0778 | K17: =K15+K16 -> -1776.2544 | L17: =L15+L16 -> -1929.1577 | M17: =M15+M16 -> -2059.0171 | N17: =N15+N16 -> -2275.0969
B18: FINANCING ACTIVITIES
B19: Dividends Paid | C19: ='Raw Data'!B111 -> -473.32 | D19: ='Raw Data'!C111 -> -693.89 | E19: ='Raw Data'!D111 -> -65.8 | F19: ='Raw Data'!E111 -> -426.72 | G19: ='Raw Data'!F111 -> -424.77 | H19: ='Raw Data'!G111 -> -708.83 | I19: ='Raw Data'!H111 -> -1073.93 | J19: =-('Financial Statements'!J29*'IS ,BS Assumptions'!I54) -> -1614 | K19: =-('Financial Statements'!K29*'IS ,BS Assumptions'!J54) -> -1936.8 | L19: =-('Financial Statements'!L29*'IS ,BS Assumptions'!K54) -> -2259.6 | M19: =-('Financial Statements'!M29*'IS ,BS Assumptions'!L54) -> -2582.4 | N19: =-('Financial Statements'!N29*'IS ,BS Assumptions'!M54) -> -2905.2
B20: Net Cash Used in Financing Activities (CFF) | C20: ='Raw Data'!B111 -> -473.32 | D20: ='Raw Data'!C111 -> -693.89 | E20: ='Raw Data'!D111 -> -65.8 | F20: ='Raw Data'!E111 -> -426.72 | G20: ='Raw Data'!F111 -> -424.77 | H20: ='Raw Data'!G111 -> -708.83 | I20: ='Raw Data'!H111 -> -1073.93 | J20: =J19 -> -1614 | K20: =K19 -> -1936.8 | L20: =L19 -> -2259.6 | M20: =M19 -> -2582.4 | N20: =N19 -> -2905.2
B21: Net Inc/(Dec) in Cash & Cash Equivalents | C21: ='Raw Data'!B112 -> -152.98 | D21: ='Raw Data'!C112 -> 197.07 | E21: ='Raw Data'!D112 -> 33.18 | F21: ='Raw Data'!E112 -> -117.43 | G21: ='Raw Data'!F112 -> -147.81 | H21: ='Raw Data'!G112 -> 135.04 | I21: ='Raw Data'!H112 -> -81.78 | J21: =J13+J17+J20 -> -2455.4313 | K21: =K13+K17+K20 -> -1788.6131 | L21: =L13+L17+L20 -> -2026.6255 | M21: =M13+M17+M20 -> -2200.9093 | N21: =N13+N17+N20 -> -2364.0109
B22: Cash at End of Year | C22: ='Raw Data'!B113 -> 64.47 | D22: ='Raw Data'!C113 -> 261.54 | E22: ='Raw Data'!D113 -> 294.72 | F22: ='Raw Data'!E113 -> 177.29 | G22: ='Raw Data'!F113 -> 29.48 | H22: ='Raw Data'!G113 -> 164.52 | I22: ='Raw Data'!H113 -> 82.74 | J22: =J5+J21 -> -2372.6913 | K22: =K5+K21 -> -4161.3044 | L22: =L5+L21 -> -6187.9299 | M22: =M5+M21 -> -8388.8392 | N22: =N5+N21 -> -10752.85

Sheet IS ,BS Assumptions
A1: CIPLA LIMITED – ASSUMPTIONS
J3: Scenarios: | L3: Y-o-Y Growth
A4: Select Case | B4: Case 2 | J4: Case 1 | K4: Optimistic Case | L4: 0.1
J5: Case 2 | K5: Base Case | L5: 0.08
J6: Case 3 | K6: Worst Case | L6: 0.06
A8: Particulars | B8: 2019 Actual | C8: 2020 Actual | D8: 2021 Actual | E8: 2022 Actual | F8: 2023 Actual | G8: 2024 Actual | H8: 2025 Actual | I8: 2026 Forecast | J8: 2027 Forecast | K8: 2028 Forecast | L8: 2029 Forecast | M8: 2030 Forecast
A9: P&L ASSUMPTIONS
A10: Revenue from Operations (INR Cr.) | B10: ='Raw Data'!B8 -> 12374.01 | C10: ='Raw Data'!C8 -> 12659.15 | D10: ='Raw Data'!D8 -> 11302.71 | E10: ='Raw Data'!E8 -> 13091.79 | F10: ='Raw Data'!F8 -> 14345.34 | G10: ='Raw Data'!G8 -> 16574.34 | H10: ='Raw Data'!H8 -> 19044.85 | I10: =H10*(1+I11) -> 20568.438 | J10: =I10*(1+J11) -> 22213.913 | K10: =J10*(1+K11) -> 23991.026 | L10: =K10*(1+L11) -> 25910.308 | M10: =L10*(1+M11) -> 27983.133
A11: Revenue Growth YoY % | C11: =(C10-B10)/B10 -> 0.02304346 | D11: =(D10-C10)/C10 -> -0.10715095 | E11: =(E10-D10)/D10 -> 0.1582877 | F11: =(F10-E10)/E10 -> 0.095750848 | G11: =(G10-F10)/F10 -> 0.15538147 | H11: =(H10-G10)/G10 -> 0.14905631 | I11: =VLOOKUP($B$4,$J$4:$L$6,3,FALSE) -> 0.08 | J11: =VLOOKUP($B$4,$J$4:$L$6,3,FALSE) -> 0.08 | K11: =VLOOKUP($B$4,$J$4:$L$6,3,FALSE) -> 0.08 | L11: =VLOOKUP($B$4,$J$4:$L$6,3,FALSE) -> 0.08 | M11: =VLOOKUP($B$4,$J$4:$L$6,3,FALSE) -> 0.08
A13: Other Income (INR Cr.) | B13: ='Raw Data'!B9 -> 577.52 | C13: ='Raw Data'!C9 -> 892.85 | D13: ='Raw Data'!D9 -> 653.91 | E13: ='Raw Data'!E9 -> 935.24 | F13: ='Raw Data'!F9 -> 826.2 | G13: ='Raw Data'!G9 -> 1433.72 | H13: ='Raw Data'!H9 -> 1279.38 | I13: =I15*I10 -> 1345.0779 | J13: =J15*J10 -> 1512.1007 | K13: =K15*K10 -> 1624.6375 | L13: =L15*L10 -> 1791.1208 | M13: =M15*M10 -> 1925.1785
A14: Other Income % of Revenue | B14: =B13/B10 -> 0.046672017 | C14: =C13/C10 -> 0.070530012 | D14: =D13/D10 -> 0.057854267 | E14: =E13/E10 -> 0.071437137 | F14: =F13/F10 -> 0.057593616 | G14: =G13/G10 -> 0.086502389 | H14: =H13/H10 -> 0.067177216
A15: Assumed Other Income % | I15: =AVERAGE(B14:H14) -> 0.065395236 | J15: =AVERAGE(C14:H14,I15:I15) -> 0.068069982 | K15: =AVERAGE(D14:H14,I15:J15) -> 0.067718549 | L15: =AVERAGE(E14:H14,I15:K15) -> 0.069127732 | M15: =AVERAGE(F14:H14,I15:L15) -> 0.068797817
A17: Raw Materials Consumed (INR Cr.) | B17: ='Raw Data'!B24 -> 4371.46 | C17: ='Raw Data'!C24 -> 4362.29 | D17: ='Raw Data'!D24 -> 4097.2 | E17: ='Raw Data'!E24 -> 5618.64 | F17: ='Raw Data'!F24 -> 4739.89 | G17: ='Raw Data'!G24 -> 4977.62 | H17: ='Raw Data'!H24 -> 5699.59
A18: Purchase of Trading Goods (INR Cr.) | B18: ='Raw Data'!B27 -> 1259.21 | C18: ='Raw Data'!C27 -> 1363.12 | D18: ='Raw Data'!D27 -> 1847.85 | E18: ='Raw Data'!E27 -> 2850.85 | F18: ='Raw Data'!F27 -> 1993.39 | G18: ='Raw Data'!G27 -> 2360.41 | H18: ='Raw Data'!H27 -> 2056.75
A19: Total Material Cost (INR Cr.) | B19: =B17+B18 -> 5630.67 | C19: =C17+C18 -> 5725.41 | D19: =D17+D18 -> 5945.05 | E19: =E17+E18 -> 8469.49 | F19: =F17+F18 -> 6733.28 | G19: =G17+G18 -> 7338.03 | H19: =H17+H18 -> 7756.34
A20: Material Cost % of Revenue | B20: =B19/B10 -> 0.45504004 | C20: =C19/C10 -> 0.45227444 | D20: =D19/D10 -> 0.52598448 | E20: =E19/E10 -> 0.6469314 | F20: =F19/F10 -> 0.46937054 | G20: =G19/G10 -> 0.44273437 | H20: =H19/H10 -> 0.40726706
A21: Assumed Material Cost % (= Average of Actuals FY2019–FY2025) | I21: =AVERAGE(B20:H20) -> 0.48565747 | J21: =AVERAGE(C20:H20,I21:I21) -> 0.49003139 | K21: =AVERAGE(D20:H20,I21:J21) -> 0.49542524 | L21: =AVERAGE(E20:H20,I21:K21) -> 0.49105964 | M21: =AVERAGE(F20:H20,I21:L21) -> 0.46879225
A22: Material Cost – Forecast (INR Cr.) | B22: =B19 -> 5630.67 | C22: =C19 -> 5725.41 | D22: =D19 -> 5945.05 | E22: =E19 -> 8469.49 | F22: =F19 -> 6733.28 | G22: =G19 -> 7338.03 | H22: =H19 -> 7756.34 | I22: =I10*I21 -> 9989.2157 | J22: =J10*J21 -> 10885.515 | K22: =K10*K21 -> 11885.76 | L22: =L10*L21 -> 12723.507 | M22: =M10*M21 -> 13118.276
A25: Employee Cost (INR Cr.) | B25: ='Raw Data'!B32 -> 1839.84 | C25: ='Raw Data'!C32 -> 1911.08 | D25: ='Raw Data'!D32 -> 1703.58 | E25: ='Raw Data'!E32 -> 1729.16 | F25: ='Raw Data'!F32 -> 2380.68 | G25: ='Raw Data'!G32 -> 2688.51 | H25: ='Raw Data'!H32 -> 3054.87
A26: Employee Cost % of Revenue | B26: =B25/B10 -> 0.14868583 | C26: =C25/C10 -> 0.15096432 | D26: =D25/D10 -> 0.15072315 | E26: =E25/E10 -> 0.13207972 | F26: =F25/F10 -> 0.16595494 | G26: =G25/G10 -> 0.16220917 | H26: =H25/H10 -> 0.16040399
A27: Assumed Employee Cost % (= Average of Actuals FY2019–FY2025) | I27: =AVERAGE(B26:H26) -> 0.15300302 | J27: =AVERAGE(C26:H26,I27:I27) -> 0.15361976 | K27: =AVERAGE(D26:H26,I27:J27) -> 0.15399911 | L27: =AVERAGE(E26:H26,I27:K27) -> 0.1544671 | M27: =AVERAGE(F26:H26,I27:L27) -> 0.1576653
A29: Employee Cost – Forecast (INR Cr.) | B29: =B25 -> 1839.84 | C29: =C25 -> 1911.08 | D29: =D25 -> 1703.58 | E29: =E25 -> 1729.16 | F29: =F25 -> 2380.68 | G29: =G25 -> 2688.51 | H29: =H25 -> 3054.87 | I29: =I10*I27 -> 3147.0331 | J29: =J10*J27 -> 3412.496 | K29: =K10*K27 -> 3694.5966 | L29: =L10*L27 -> 4002.2902 | M29: =M10*M27 -> 4411.969
A31: Other Operating Expenses (INR Cr.) | B31: ='Raw Data'!B30+'Raw Data'!B37+'Raw Data'!B44+'Raw Data'!B50+'Raw Data'!B57 -> 3949.95 | C31: ='Raw Data'!C30+'Raw Data'!C37+'Raw Data'!C44+'Raw Data'!C50+'Raw Data'!C57 -> 4278.7 | D31: ='Raw Data'!D30+'Raw Data'!D37+'Raw Data'!D44+'Raw Data'!D50+'Raw Data'!D57 -> 2899.99 | E31: ='Raw Data'!E30+'Raw Data'!E37+'Raw Data'!E44+'Raw Data'!E50+'Raw Data'!E57 -> 3448.82 | F31: ='Raw Data'!F30+'Raw Data'!F37+'Raw Data'!F44+'Raw Data'!F50+'Raw Data'!F57 -> 4457.55 | G31: ='Raw Data'!G30+'Raw Data'!G37+'Raw Data'!G44+'Raw Data'!G50+'Raw Data'!G57 -> 4995.56 | H31: ='Raw Data'!H30+'Raw Data'!H37+'Raw Data'!H44+'Raw Data'!H50+'Raw Data'!H57 -> 5542.32
A32: Other Opex % of Revenue | B32: =B31/B10 -> 0.31921342 | C32: =C31/C10 -> 0.33799268 | D32: =D31/D10 -> 0.25657475 | E32: =E31/E10 -> 0.2634338 | F32: =F31/F10 -> 0.31073157 | G32: =G31/G10 -> 0.30140325 | H32: =H31/H10 -> 0.29101411
A33: Assumed Other Opex % (= Average of Actuals FY2019–FY2025) | I33: =AVERAGE(B32:H32) -> 0.2971948 | J33: =AVERAGE(C32:H32,I33:I33) -> 0.29404928 | K33: =AVERAGE(D32:H32,I33:J33) -> 0.28777165 | L33: =AVERAGE(E32:H32,I33:K33) -> 0.29222835 | M33: =AVERAGE(F32:H32,I33:L33) -> 0.29634186
A34: Other Opex – Forecast (INR Cr.) | B34: =B31 -> 3949.95 | C34: =C31 -> 4278.7 | D34: =D31 -> 2899.99 | E34: =E31 -> 3448.82 | F34: =F31 -> 4457.55 | G34: =G31 -> 4995.56 | H34: =H31 -> 5542.32 | I34: =I10*I33 -> 6112.8327 | J34: =J10*J33 -> 6531.9851 | K34: =K10*K33 -> 6903.9372 | L34: =L10*L33 -> 7571.7266 | M34: =M10*M33 -> 8292.5736
A36: Finance Cost / Interest (INR Cr.) | B36: ='Raw Data'!B67 -> 16.97 | C36: ='Raw Data'!C67 -> 36.05 | D36: ='Raw Data'!D67 -> 45.07 | E36: ='Raw Data'!E67 -> 26.93 | F36: ='Raw Data'!F67 -> 22.27 | G36: ='Raw Data'!G67 -> 20.25 | H36: ='Raw Data'!H67 -> 15.11 | I36: 18 | J36: 18 | K36: 20 | L36: 20 | M36: 22
A37: Depreciation & Amortisation – from PPE Schedule | B37: ='Raw Data'!B71 -> 569.72 | C37: ='Raw Data'!C71 -> 599.78 | D37: ='Raw Data'!D71 -> 468.62 | E37: ='Raw Data'!E71 -> 460.01 | F37: ='Raw Data'!F71 -> 595.91 | G37: ='Raw Data'!G71 -> 587.59 | H37: ='Raw Data'!H71 -> 573.89 | I37: ='PPE Schedule'!J12 -> 704.5056 | J37: ='PPE Schedule'!K12 -> 713.53092 | K37: ='PPE Schedule'!L12 -> 736.83114 | L37: ='PPE Schedule'!M12 -> 721.05845 | M37: ='PPE Schedule'!N12 -> 761.29694
A39: TAX ASSUMPTIONS
A40: Historical Effective Tax Rate | B40: ='Raw Data'!B73/'Raw Data'!B72 -> 0.23123518 | C40: ='Raw Data'!C73/'Raw Data'!C72 -> 0.18417777 | D40: ='Raw Data'!D73/'Raw Data'!D72 -> 0.23577221 | E40: ='Raw Data'!E73/'Raw Data'!E72 -> 0.23258021 | F40: ='Raw Data'!F73/'Raw Data'!F72 -> 0.26714884 | G40: ='Raw Data'!G73/'Raw Data'!G72 -> 0.23101376 | H40: ='Raw Data'!H73/'Raw Data'!H72 -> 0.21028874
A41: Assumed Tax Rate – 23.62% from Parameters (= Average of Actuals FY2019–FY2025) | I41: =AVERAGE(B40:H40) -> 0.22745953 | J41: =AVERAGE(C40:H40,I41:I41) -> 0.22692015 | K41: =AVERAGE(D40:H40,I41:J41) -> 0.2330262 | L41: =AVERAGE(E40:H40,I41:K41) -> 0.23263392 | M41: =AVERAGE(F40:H40,I41:L41) -> 0.23264159
A44: Particulars | B44: 2019 Actual | C44: 2020 Actual | D44: 2021 Actual | E44: 2022 Actual | F44: 2023 Actual | G44: 2024 Actual | H44: 2025 Actual | I44: 2026 Forecast | J44: 2027 Forecast | K44: 2028 Forecast | L44: 2029 Forecast | M44: 2030 Forecast
A45: BALANCE SHEET ASSUMPTIONS
A46: Inventory Days (Historical) | B46: ='Raw Data'!K45/'Raw Data'!B8*365 -> 84.610377 | C46: ='Raw Data'!L45/'Raw Data'!C8*365 -> 87.114569 | D46: ='Raw Data'!M45/'Raw Data'!D8*365 -> 99.650495 | E46: ='Raw Data'!N45/'Raw Data'!E8*365 -> 97.184621 | F46: ='Raw Data'!O45/'Raw Data'!F8*365 -> 83.388501 | G46: ='Raw Data'!P45/'Raw Data'!G8*365 -> 71.665731 | H46: ='Raw Data'!Q45/'Raw Data'!H8*365 -> 69.131487 | I46: 84 | J46: 82 | K46: 80 | L46: 78 | M46: 76
A47: Assumed Inventory Days (= Average of Actuals FY2019–FY2025) | I47: =AVERAGE(B46:H46) -> 84.677969 | J47: =AVERAGE(C46:H46,I47:I47) -> 84.687625 | K47: =AVERAGE(D46:H46,I47:J47) -> 84.340919 | L47: =AVERAGE(E46:H46,I47:K47) -> 82.153836 | M47: =AVERAGE(F46:H46,I47:L47) -> 80.006581
A48: Receivable Days (Historical) | B48: ='Raw Data'!K46/'Raw Data'!B8*365 -> 93.469009 | C48: ='Raw Data'!L46/'Raw Data'!C8*365 -> 102.65291 | D48: ='Raw Data'!M46/'Raw Data'!D8*365 -> 98.021629 | E48: ='Raw Data'!N46/'Raw Data'!E8*365 -> 77.910293 | F48: ='Raw Data'!O46/'Raw Data'!F8*365 -> 73.49417 | G48: ='Raw Data'!P46/'Raw Data'!G8*365 -> 59.05748 | H48: ='Raw Data'!Q46/'Raw Data'!H8*365 -> 73.977813 | I48: 72 | J48: 70 | K48: 68 | L48: 66 | M48: 65
A49: Assumed Receivable Days (= Average of Actuals FY2019–FY2025) | I49: =AVERAGE(B48:H48) -> 82.654757 | J49: =AVERAGE(C48:H48,I49:I49) -> 81.109864 | K49: =AVERAGE(D48:H48,I49:J49) -> 78.032287 | L49: =AVERAGE(E48:H48,I49:K49) -> 75.176666 | M49: =AVERAGE(F48:H48,I49:L49) -> 74.786148
A50: Payable Days (Historical) | B50: ='Raw Data'!K23/'Raw Data'!B8*365 -> 43.695839 | C50: ='Raw Data'!L23/'Raw Data'!C8*365 -> 46.482094 | D50: ='Raw Data'!M23/'Raw Data'!D8*365 -> 48.294068 | E50: ='Raw Data'!N23/'Raw Data'!E8*365 -> 43.76418 | F50: ='Raw Data'!O23/'Raw Data'!F8*365 -> 41.700357 | G50: ='Raw Data'!P23/'Raw Data'!G8*365 -> 37.09913 | H50: ='Raw Data'!Q23/'Raw Data'!H8*365 -> 36.101841 | I50: 34 | J50: 34 | K50: 34 | L50: 35 | M50: 35
A51: Assumed Payable Days (= Average of Actuals FY2019–FY2025) | I51: =AVERAGE(B50:H50) -> 42.448216 | J51: =AVERAGE(C50:H50,I51:I51) -> 42.269984 | K51: =AVERAGE(D50:H50,I51:J51) -> 41.668254 | L51: =AVERAGE(E50:H50,I51:K51) -> 40.721709 | M51: =AVERAGE(F50:H50,I51:L51) -> 40.28707
A52: Capex % of Revenue (Actuals from CF Statement | Forecast = Average of Actuals) | B52: =-'Raw Data'!B109/'Raw Data'!B8 -> 0.025218179 | C52: =-'Raw Data'!C109/'Raw Data'!C8 -> 0.035524502 | D52: =-'Raw Data'!D109/'Raw Data'!D8 -> 0.045738588 | E52: =-'Raw Data'!E109/'Raw Data'!E8 -> 0.025334962 | F52: =-'Raw Data'!F109/'Raw Data'!F8 -> 0.047691445 | G52: =-'Raw Data'!G109/'Raw Data'!G8 -> 0.04119078 | H52: =-'Raw Data'!H109/'Raw Data'!H8 -> 0.038261262 | I52: =AVERAGE(B52:H52) -> 0.036994246 | J52: =AVERAGE(C52:I52) -> 0.038676541 | K52: =AVERAGE(D52:J52) -> 0.039126832 | L52: =AVERAGE(E52:K52) -> 0.038182296 | M52: =AVERAGE(F52:L52) -> 0.040017629
A53: Dividend Per Share INR (User Input) | B53: ='Raw Data'!B96 -> 3 | C53: ='Raw Data'!C96 -> 4 | D53: ='Raw Data'!D96 -> 5 | E53: ='Raw Data'!E96 -> 5 | F53: ='Raw Data'!F96 -> 8.5 | G53: ='Raw Data'!G96 -> 13 | H53: ='Raw Data'!H96 -> 16 | I53: 20 | J53: 24 | K53: 28 | L53: 32 | M53: 36
A54: Shares Outstanding (Crores) | B54: 80.6 | C54: 80.6 | D54: 80.6 | E54: 80.6 | F54: 80.6 | G54: 80.6 | H54: 80.6 | I54: 80.7 | J54: 80.7 | K54: 80.7 | L54: 80.7 | M54: 80.7

Sheet Financial Statements
B1: CIPLA LIMITED – PROJECTED FINANCIAL STATEMENTS
B5: Particulars | C5: 2019 Actual | D5: 2020 Actual | E5: 2021 Actual | F5: 2022 Actual | G5: 2023 Actual | H5: 2024 Actual | I5: 2025 Actual | J5: 2026 Forecast | K5: 2027 Forecast | L5: 2028 Forecast | M5: 2029 Forecast | N5: 2030 Forecast
B6: INCOME STATEMENT
B7: Revenue from Operations | C7: ='IS ,BS Assumptions'!B10 -> 12374.01 | D7: ='IS ,BS Assumptions'!C10 -> 12659.15 | E7: ='IS ,BS Assumptions'!D10 -> 11302.71 | F7: ='IS ,BS Assumptions'!E10 -> 13091.79 | G7: ='IS ,BS Assumptions'!F10 -> 14345.34 | H7: ='IS ,BS Assumptions'!G10 -> 16574.34 | I7: ='IS ,BS Assumptions'!H10 -> 19044.85 | J7: ='IS ,BS Assumptions'!I10 -> 20568.438 | ... N7: ='IS ,BS Assumptions'!M10 -> 27983.133
B8: Other Income | C8: ='IS ,BS Assumptions'!B13 -> 577.52 | D8: ='IS ,BS Assumptions'!C13 -> 892.85 | E8: ='IS ,BS Assumptions'!D13 -> 653.91 | F8: ='IS ,BS Assumptions'!E13 -> 935.24 | G8: ='IS ,BS Assumptions'!F13 -> 826.2 | H8: ='IS ,BS Assumptions'!G13 -> 1433.72 | I8: ='IS ,BS Assumptions'!H13 -> 1279.38 | J8: ='IS ,BS Assumptions'!I13 -> 1345.0779 | ... N8: ='IS ,BS Assumptions'!M13 -> 1925.1785
B9: Raw Materials & Trading Goods | C9: ='IS ,BS Assumptions'!B22 -> 5630.67 | D9: ='IS ,BS Assumptions'!C22 -> 5725.41 | E9: ='IS ,BS Assumptions'!D22 -> 5945.05 | F9: ='IS ,BS Assumptions'!E22 -> 8469.49 | G9: ='IS ,BS Assumptions'!F22 -> 6733.28 | H9: ='IS ,BS Assumptions'!G22 -> 7338.03 | I9: ='IS ,BS Assumptions'!H22 -> 7756.34 | J9: ='IS ,BS Assumptions'!I22 -> 9989.2157 | ... N9: ='IS ,BS Assumptions'!M22 -> 13118.276
B10: Employee Benefit Expenses | C10: ='IS ,BS Assumptions'!B29 -> 1839.84 | D10: ='IS ,BS Assumptions'!C29 -> 1911.08 | E10: ='IS ,BS Assumptions'!D29 -> 1703.58 | F10: ='IS ,BS Assumptions'!E29 -> 1729.16 | G10: ='IS ,BS Assumptions'!F29 -> 2380.68 | H10: ='IS ,BS Assumptions'!G29 -> 2688.51 | I10: ='IS ,BS Assumptions'!H29 -> 3054.87 | J10: ='IS ,BS Assumptions'!I29 -> 3147.0331 | ... N10: ='IS ,BS Assumptions'!M29 -> 4411.969
B11: Other Operating Expenses | C11: ='IS ,BS Assumptions'!B34 -> 3949.95 | D11: ='IS ,BS Assumptions'!C34 -> 4278.7 | E11: ='IS ,BS Assumptions'!D34 -> 2899.99 | F11: ='IS ,BS Assumptions'!E34 -> 3448.82 | G11: ='IS ,BS Assumptions'!F34 -> 4457.55 | H11: ='IS ,BS Assumptions'!G34 -> 4995.56 | I11: ='IS ,BS Assumptions'!H34 -> 5542.32 | J11: ='IS ,BS Assumptions'!I34 -> 6112.8327 | ... N11: ='IS ,BS Assumptions'!M34 -> 8292.5736
B12: Total Operating Expenditure | C12: =C9+C10+C11 -> 11420.46 | D12: =D9+D10+D11 -> 11915.19 | E12: =E9+E10+E11 -> 10548.62 | F12: =F9+F10+F11 -> 13647.47 | G12: =G9+G10+G11 -> 13571.51 | H12: =H9+H10+H11 -> 15022.1 | I12: =I9+I10+I11 -> 16353.53 | J12: =J9+J10+J11 -> 19249.082 | ... N12: =N9+N10+N11 -> 25822.818
B14: EBITDA | C14: =C7+C8-C12 -> 1531.07 | D14: =D7+D8-D12 -> 1636.81 | E14: =E7+E8-E12 -> 1408 | F14: =F7+F8-F12 -> 379.56 | G14: =G7+G8-G12 -> 1600.03 | H14: =H7+H8-H12 -> 2985.96 | I14: =I7+I8-I12 -> 3970.7 | J14: =J7+J8-J12 -> 2664.4344 | ... N14: =N7+N8-N12 -> 4085.493
B15: EBITDA Margin (%) | C15: =C14/C7 -> 0.12373273 | D15: =D14/D7 -> 0.12929857 | E15: =E14/E7 -> 0.12457189 | F15: =F14/F7 -> 0.028992216 | G15: =G14/G7 -> 0.11153657 | H15: =H14/H7 -> 0.18015559 | I15: =I14/I7 -> 0.20849206 | J15: =J14/J7 -> 0.12953995 | ... N15: =N14/N7 -> 0.14599841
B17: Depreciation & Amortisation | C17: ='IS ,BS Assumptions'!B37 -> 569.72 | D17: ='IS ,BS Assumptions'!C37 -> 599.78 | E17: ='IS ,BS Assumptions'!D37 -> 468.62 | F17: ='IS ,BS Assumptions'!E37 -> 460.01 | G17: ='IS ,BS Assumptions'!F37 -> 595.91 | H17: ='IS ,BS Assumptions'!G37 -> 587.59 | I17: ='IS ,BS Assumptions'!H37 -> 573.89 | J17: ='IS ,BS Assumptions'!I37 -> 704.5056 | ... N17: ='IS ,BS Assumptions'!M37 -> 761.29694
B18: Finance Costs / Interest | C18: ='IS ,BS Assumptions'!B36 -> 16.97 | D18: ='IS ,BS Assumptions'!C36 -> 36.05 | E18: ='IS ,BS Assumptions'!D36 -> 45.07 | F18: ='IS ,BS Assumptions'!E36 -> 26.93 | G18: ='IS ,BS Assumptions'!F36 -> 22.27 | H18: ='IS ,BS Assumptions'!G36 -> 20.25 | I18: ='IS ,BS Assumptions'!H36 -> 15.11 | J18: ='IS ,BS Assumptions'!I36 -> 18 | ... N18: ='IS ,BS Assumptions'!M36 -> 22
B20: EBIT | C20: =C14-C17 -> 961.35 | D20: =D14-D17 -> 1037.03 | E20: =E14-E17 -> 939.38 | F20: =F14-F17 -> -80.45 | G20: =G14-G17 -> 1004.12 | H20: =H14-H17 -> 2398.37 | I20: =I14-I17 -> 3396.81 | J20: =J14-J17 -> 1959.9288 | ... N20: =N14-N17 -> 3324.1961
B21: EBIT Margin (%) | C21: =C20/C7 -> 0.077691064 | D21: =D20/D7 -> 0.081919402 | E21: =E20/E7 -> 0.083111042 | F21: =F20/F7 -> -0.0061450726 | G21: =G20/G7 -> 0.06999625 | H21: =H20/H7 -> 0.1447038 | I21: =I20/I7 -> 0.17835845 | J21: =J20/J7 -> 0.095288167 | ... N21: =N20/N7 -> 0.11879285
B23: Profit Before Tax (PBT) | C23: ='Raw Data'!B72 -> 2492.83 | D23: ='Raw Data'!C72 -> 2964.31 | E23: ='Raw Data'!D72 -> 3207.63 | F23: ='Raw Data'!E72 -> 3814.77 | G23: ='Raw Data'!F72 -> 3375.01 | H23: ='Raw Data'!G72 -> 5310.03 | I23: ='Raw Data'!H72 -> 6468.82 | J23: =J20-J18 -> 1941.9288 | K23: =K20-K18 -> 2164.4869 | L23: =L20-L18 -> 2374.5387 | M23: =M20-M18 -> 2662.8471 | N23: =N20-N18 -> 3302.1961
B24: Tax Expense | C24: ='Raw Data'!B73 -> 576.43 | D24: ='Raw Data'!C73 -> 545.96 | E24: ='Raw Data'!D73 -> 756.27 | F24: ='Raw Data'!E73 -> 887.24 | G24: ='Raw Data'!F73 -> 901.63 | H24: ='Raw Data'!G73 -> 1226.69 | I24: ='Raw Data'!H73 -> 1360.32 | J24: =J23*'IS ,BS Assumptions'!I41 -> 441.7102 | K24: =K23*'IS ,BS Assumptions'!J41 -> 491.16569 | L24: =L23*'IS ,BS Assumptions'!K41 -> 553.32973 | M24: =M23*'IS ,BS Assumptions'!L41 -> 619.46856 | N24: =N23*'IS ,BS Assumptions'!M41 -> 768.22815
B25: Net Profit / PAT | C25: ='Raw Data'!B77 -> 1888.41 | D25: ='Raw Data'!C77 -> 2318.17 | E25: ='Raw Data'!D77 -> 2468.28 | F25: ='Raw Data'!E77 -> 2957.93 | G25: ='Raw Data'!F77 -> 2513.47 | H25: ='Raw Data'!G77 -> 4077.25 | I25: ='Raw Data'!H77 -> 5157.65 | J25: =J23-J24 -> 1500.2186 | K25: =K23-K24 -> 1673.3212 | L25: =L23-L24 -> 1821.2089 | M25: =M23-M24 -> 2043.3786 | N25: =N23-N24 -> 2533.9679
B26: PAT Margin (%) | C26: =C25/C7 -> 0.152611 | D26: =D25/D7 -> 0.18312209 | E26: =E25/E7 -> 0.21837949 | F26: =F25/F7 -> 0.22593778 | G26: =G25/G7 -> 0.1752116 | H26: =H25/H7 -> 0.24599773 | I26: =I25/I7 -> 0.27081599 | J26: =J25/J7 -> 0.072937894 | ... N26: =N25/N7 -> 0.090553404
B28: Earnings Per Share (INR) | C28: ='Raw Data'!B97 -> 23.44 | D28: ='Raw Data'!C97 -> 28.75 | E28: ='Raw Data'!D97 -> 30.61 | F28: ='Raw Data'!E97 -> 36.66 | G28: ='Raw Data'!F97 -> 31.14 | H28: ='Raw Data'!G97 -> 50.5 | I28: ='Raw Data'!H97 -> 63.86 | J28: =J25/'IS ,BS Assumptions'!I54 -> 18.590069 | K28: =K25/'IS ,BS Assumptions'!J54 -> 20.735083 | L28: =L25/'IS ,BS Assumptions'!K54 -> 22.567645 | M28: =M25/'IS ,BS Assumptions'!L54 -> 25.320676 | N28: =N25/'IS ,BS Assumptions'!M54 -> 31.39985
B29: Dividend Per Share (INR) | C29: ='Raw Data'!B96 -> 3 | D29: ='Raw Data'!C96 -> 4 | E29: ='Raw Data'!D96 -> 5 | F29: ='Raw Data'!E96 -> 5 | G29: ='Raw Data'!F96 -> 8.5 | H29: ='Raw Data'!G96 -> 13 | I29: ='Raw Data'!H96 -> 16 | J29: ='IS ,BS Assumptions'!I53 -> 20 | K29: ='IS ,BS Assumptions'!J53 -> 24 | L29: ='IS ,BS Assumptions'!K53 -> 28 | M29: ='IS ,BS Assumptions'!L53 -> 32 | N29: ='IS ,BS Assumptions'!M53 -> 36
B34: Particulars | C34: 2019 Actual | D34: 2020 Actual | E34: 2021 Actual | F34: 2022 Actual | G34: 2023 Actual | H34: 2024 Actual | I34: 2025 Actual | J34: 2026 Forecast | K34: 2027 Forecast | L34: 2028 Forecast | M34: 2029 Forecast | N34: 2030 Forecast
B35: BALANCE SHEET – EQUITY & LIABILITIES
B36: Share Capital | C36: ='Raw Data'!K7 -> 161.14 | D36: ='Raw Data'!L7 -> 161.25 | E36: ='Raw Data'!M7 -> 161.29 | F36: ='Raw Data'!N7 -> 161.36 | G36: ='Raw Data'!O7 -> 161.43 | H36: ='Raw Data'!P7 -> 161.47 | I36: ='Raw Data'!Q7 -> 161.52 | J36: 161.57 | K36: 161.62 | L36: 161.67 | M36: 161.72 | N36: 161.77
B37: Reserves & Surplus | C37: ='Raw Data'!K9 -> 15620.77 | D37: ='Raw Data'!L9 -> 17241.71 | E37: ='Raw Data'!M9 -> 19766.27 | F37: ='Raw Data'!N9 -> 22352.19 | G37: ='Raw Data'!O9 -> 24476.66 | H37: ='Raw Data'!P9 -> 27812.45 | I37: ='Raw Data'!Q9 -> 31937.72 | J37: =I37+J25-J29*'IS ,BS Assumptions'!I54 -> 31823.939 | K37: =J37+K25-K29*'IS ,BS Assumptions'!J54 -> 31560.46 | L37: =K37+L25-L29*'IS ,BS Assumptions'!K54 -> 31122.069 | M37: =L37+M25-M29*'IS ,BS Assumptions'!L54 -> 30583.047 | N37: =M37+N25-N29*'IS ,BS Assumptions'!M54 -> 30211.815
B38: Total Shareholders' Equity | C38: ='Raw Data'!K10 -> 15781.91 | D38: ='Raw Data'!L10 -> 17402.96 | E38: ='Raw Data'!M10 -> 19927.56 | F38: ='Raw Data'!N10 -> 22513.55 | G38: ='Raw Data'!O10 -> 24638.09 | H38: ='Raw Data'!P10 -> 27973.92 | I38: ='Raw Data'!Q10 -> 32099.24 | J38: =J36+J37 -> 31985.509 | K38: =K36+K37 -> 31722.08 | L38: =L36+L37 -> 31283.739 | M38: =M36+M37 -> 30744.767 | N38: =N36+N37 -> 30373.585
B39: Non-Current Liabilities
B40: Long-Term Borrowings | C40: ='Raw Data'!K12 -> 0 | D40: ='Raw Data'!L12 -> 0 | E40: ='Raw Data'!M12 -> 0 | F40: ='Raw Data'!N12 -> 0 | G40: ='Raw Data'!O12 -> 0 | H40: ='Raw Data'!P12 -> 0 | I40: ='Raw Data'!Q12 -> 0 | J40: 0 | K40: 0 | L40: 0 | M40: 0 | N40: 0
B41: Lease Liabilities (Non-Current) | C41: ='Raw Data'!K13 -> 0 | D41: ='Raw Data'!L13 -> 0 | E41: ='Raw Data'!M13 -> 29.46 | F41: ='Raw Data'!N13 -> 15.53 | G41: ='Raw Data'!O13 -> 35.53 | H41: ='Raw Data'!P13 -> 29.55 | I41: ='Raw Data'!Q13 -> 86.18 | J41: =I41*1.05 -> 90.489 | K41: =J41*1.05 -> 95.01345 | L41: =K41*1.05 -> 99.764123 | M41: =L41*1.05 -> 104.75233 | N41: =M41*1.05 -> 109.98995
B42: Deferred Tax Liabilities (Net) | C42: ='Raw Data'!K14 -> 42.84 | D42: ='Raw Data'!L14 -> 112.97 | E42: ='Raw Data'!M14 -> 104.91 | F42: ='Raw Data'!N14 -> 79.25 | G42: ='Raw Data'!O14 -> 36.13 | H42: ='Raw Data'!P14 -> 32.64 | I42: ='Raw Data'!Q14 -> 0 | J42: 0 | K42: 0 | L42: 0 | M42: 0 | N42: 0
B43: Other LT Liabilities & Provisions | C43: ='Raw Data'!K17+'Raw Data'!K18 -> 225.98 | D43: ='Raw Data'!L17+'Raw Data'!L18 -> 270.44 | E43: ='Raw Data'!M17+'Raw Data'!M18 -> 209.87 | F43: ='Raw Data'!N17+'Raw Data'!N18 -> 181.38 | G43: ='Raw Data'!O17+'Raw Data'!O18 -> 186.98 | H43: ='Raw Data'!P17+'Raw Data'!P18 -> 154.87 | I43: ='Raw Data'!Q17+'Raw Data'!Q18 -> 196.88 | J43: =I43*1.05 -> 206.724 | K43: =J43*1.05 -> 217.0602 | L43: =K43*1.05 -> 227.91321 | M43: =L43*1.05 -> 239.30887 | N43: =M43*1.05 -> 251.27431
B44: Total Non-Current Liabilities | C44: ='Raw Data'!K19 -> 268.82 | D44: ='Raw Data'!L19 -> 383.41 | E44: ='Raw Data'!M19 -> 344.24 | F44: ='Raw Data'!N19 -> 276.16 | G44: ='Raw Data'!O19 -> 258.64 | H44: ='Raw Data'!P19 -> 217.06 | I44: ='Raw Data'!Q19 -> 283.06 | J44: =J40+J41+J42+J43 -> 297.213 | K44: =K40+K41+K42+K43 -> 312.07365 | L44: =L40+L41+L42+L43 -> 327.67733 | M44: =M40+M41+M42+M43 -> 344.0612 | N44: =N40+N41+N42+N43 -> 361.26426
B45: Current Liabilities
B46: Short-Term Borrowings | C46: ='Raw Data'!K21 -> 0 | D46: ='Raw Data'!L21 -> 6.06 | E46: ='Raw Data'!M21 -> 0 | F46: ='Raw Data'!N21 -> 0 | G46: ='Raw Data'!O21 -> 0 | H46: ='Raw Data'!P21 -> 0 | I46: ='Raw Data'!Q21 -> 0 | J46: 0 | K46: 0 | L46: 0 | M46: 0 | N46: 0
B47: Trade Payables | C47: ='Raw Data'!K23 -> 1481.35 | D47: ='Raw Data'!L23 -> 1612.12 | E47: ='Raw Data'!M23 -> 1495.49 | F47: ='Raw Data'!N23 -> 1569.73 | G47: ='Raw Data'!O23 -> 1638.92 | H47: ='Raw Data'!P23 -> 1684.64 | I47: ='Raw Data'!Q23 -> 1883.71 | J47: ='IS ,BS Assumptions'!I51/365*J7 -> 2392.037 | K47: ='IS ,BS Assumptions'!J51/365*K7 -> 2572.5527 | L47: ='IS ,BS Assumptions'!K51/365*L7 -> 2738.8059 | M47: ='IS ,BS Assumptions'!L51/365*M7 -> 2890.7179 | N47: ='IS ,BS Assumptions'!M51/365*N7 -> 3088.6532
B48: Other Current Liabilities | C48: ='Raw Data'!K24 -> 406.59 | D48: ='Raw Data'!L24 -> 455.04 | E48: ='Raw Data'!M24 -> 548.66 | F48: ='Raw Data'!N24 -> 450.3 | G48: ='Raw Data'!O24 -> 399.52 | H48: ='Raw Data'!P24 -> 407.08 | I48: ='Raw Data'!Q24 -> 435.65 | J48: =I48*1.06 -> 461.789 | K48: =J48*1.06 -> 489.49634 | L48: =K48*1.06 -> 518.86612 | M48: =L48*1.06 -> 549.99809 | N48: =M48*1.06 -> 582.99797
B49: Short-Term Provisions | C49: ='Raw Data'!K25 -> 480.14 | D49: ='Raw Data'!L25 -> 546.07 | E49: ='Raw Data'!M25 -> 625.13 | F49: ='Raw Data'!N25 -> 631.39 | G49: ='Raw Data'!O25 -> 646.74 | H49: ='Raw Data'!P25 -> 754.53 | I49: ='Raw Data'!Q25 -> 832.86 | J49: =I49*1.06 -> 882.8316 | K49: =J49*1.06 -> 935.8015 | L49: =K49*1.06 -> 991.94959 | M49: =L49*1.06 -> 1051.4666 | N49: =M49*1.06 -> 1114.5546
B50: Total Current Liabilities | C50: ='Raw Data'!K26 -> 2368.08 | D50: ='Raw Data'!L26 -> 2619.29 | E50: ='Raw Data'!M26 -> 2691.94 | F50: ='Raw Data'!N26 -> 2659.34 | G50: ='Raw Data'!O26 -> 2699.74 | H50: ='Raw Data'!P26 -> 2862.25 | I50: ='Raw Data'!Q26 -> 3183.42 | J50: =J46+J47+J48+J49 -> 3736.6576 | K50: =K46+K47+K48+K49 -> 3997.8506 | L50: =L46+L47+L48+L49 -> 4249.6216 | M50: =M46+M47+M48+M49 -> 4492.1825 | N50: =N46+N47+N48+N49 -> 4786.2058
B52: TOTAL EQUITY & LIABILITIES | C52: ='Raw Data'!K28 -> 18418.81 | D52: ='Raw Data'!L28 -> 20405.66 | E52: ='Raw Data'!M28 -> 22963.74 | F52: ='Raw Data'!N28 -> 25449.05 | G52: ='Raw Data'!O28 -> 27596.47 | H52: ='Raw Data'!P28 -> 31053.23 | I52: ='Raw Data'!Q28 -> 35565.72 | J52: =J38+J44+J50 -> 36019.379 | K52: =K38+K44+K50 -> 36032.004 | L52: =L38+L44+L50 -> 35861.038 | M52: =M38+M44+M50 -> 35581.011 | N52: =N38+N44+N50 -> 35521.055
B54: BALANCE SHEET – ASSETS
B55: Non-Current Assets
B56: Net Fixed Assets (PPE) – from PPE Schedule | C56: ='Raw Data'!K30 -> 4424.79 | D56: ='Raw Data'!L30 -> 4344.27 | E56: ='Raw Data'!M30 -> 4297.77 | F56: ='Raw Data'!N30 -> 4114.25 | G56: ='Raw Data'!O30 -> 4251.53 | H56: ='Raw Data'!P30 -> 4273.41 | I56: ='Raw Data'!Q30 -> 4403.16 | J56: ='PPE Schedule'!J10 -> 4459.5682 | K56: ='PPE Schedule'!K10 -> 4605.1946 | L56: ='PPE Schedule'!L10 -> 4807.0564 | M56: ='PPE Schedule'!M10 -> 5075.3129 | N56: ='PPE Schedule'!N10 -> 5433.8346
B57: Non-Current Investments | C57: ='Raw Data'!K36 -> 3865.46 | D57: ='Raw Data'!L36 -> 6481.76 | E57: ='Raw Data'!M36 -> 7844.78 | F57: ='Raw Data'!N36 -> 8998.23 | G57: ='Raw Data'!O36 -> 9199.63 | H57: ='Raw Data'!P36 -> 9525.66 | I57: ='Raw Data'!Q36 -> 10614.55 | J57: =I57*1.08 -> 11463.714 | K57: =J57*1.08 -> 12380.811 | L57: =K57*1.08 -> 13371.276 | M57: =L57*1.08 -> 14440.978 | N57: =M57*1.08 -> 15596.256
B58: Long-Term Loans & Advances | C58: ='Raw Data'!K40 -> 609.23 | D58: ='Raw Data'!L40 -> 539.32 | E58: ='Raw Data'!M40 -> 615.26 | F58: ='Raw Data'!N40 -> 555.68 | G58: ='Raw Data'!O40 -> 748.77 | H58: ='Raw Data'!P40 -> 1904.67 | I58: ='Raw Data'!Q40 -> 1735.25 | J58: =I58*1.03 -> 1787.3075 | K58: =J58*1.03 -> 1840.9267 | L58: =K58*1.03 -> 1896.1545 | M58: =L58*1.03 -> 1953.0392 | N58: =M58*1.03 -> 2011.6303
B59: Other Non-Current Assets | C59: ='Raw Data'!K37+'Raw Data'!K41 -> 40.68 | D59: ='Raw Data'!L37+'Raw Data'!L41 -> 13.25 | E59: ='Raw Data'!M37+'Raw Data'!M41 -> 13.75 | F59: ='Raw Data'!N37+'Raw Data'!N41 -> 346.98 | G59: ='Raw Data'!O37+'Raw Data'!O41 -> 25.41 | H59: ='Raw Data'!P37+'Raw Data'!P41 -> 442.69 | I59: ='Raw Data'!Q37+'Raw Data'!Q41 -> 403.99 | J59: =I59*1.03 -> 416.1097 | K59: =J59*1.03 -> 428.59299 | L59: =K59*1.03 -> 441.45078 | M59: =L59*1.03 -> 454.6943 | N59: =M59*1.03 -> 468.33513
B60: Total Non-Current Assets | C60: ='Raw Data'!K42 -> 8940.16 | D60: ='Raw Data'!L42 -> 11378.6 | E60: ='Raw Data'!M42 -> 12771.56 | F60: ='Raw Data'!N42 -> 14015.14 | G60: ='Raw Data'!O42 -> 14225.34 | H60: ='Raw Data'!P42 -> 16146.43 | I60: ='Raw Data'!Q42 -> 17156.95 | J60: =J56+J57+J58+J59 -> 18126.699 | K60: =K56+K57+K58+K59 -> 19255.525 | L60: =L56+L57+L58+L59 -> 20515.938 | M60: =M56+M57+M58+M59 -> 21924.024 | N60: =N56+N57+N58+N59 -> 23510.056
B61: Current Assets
B62: Inventories | C62: ='Raw Data'!K45 -> 2868.41 | D62: ='Raw Data'!L45 -> 3021.36 | E62: ='Raw Data'!M45 -> 3085.81 | F62: ='Raw Data'!N45 -> 3485.81 | G62: ='Raw Data'!O45 -> 3277.36 | H62: ='Raw Data'!P45 -> 3254.28 | I62: ='Raw Data'!Q45 -> 3607.12 | J62: ='IS ,BS Assumptions'!I47/365*J7 -> 4771.7632 | K62: ='IS ,BS Assumptions'!J47/365*K7 -> 5154.0919 | L62: ='IS ,BS Assumptions'!K47/365*L7 -> 5543.6306 | M62: ='IS ,BS Assumptions'!L47/365*M7 -> 5831.8663 | N62: ='IS ,BS Assumptions'!M47/365*N7 -> 6133.7939
B63: Trade Receivables | C63: ='Raw Data'!K46 -> 3168.73 | D63: ='Raw Data'!L46 -> 3560.27 | E63: ='Raw Data'!M46 -> 3035.37 | F63: ='Raw Data'!N46 -> 2794.48 | G63: ='Raw Data'!O46 -> 2888.49 | H63: ='Raw Data'!P46 -> 2681.75 | I63: ='Raw Data'!Q46 -> 3859.99 | J63: ='IS ,BS Assumptions'!I49/365*J7 -> 4657.7514 | K63: ='IS ,BS Assumptions'!J49/365*K7 -> 4936.3492 | L63: ='IS ,BS Assumptions'!K49/365*L7 -> 5128.9716 | M63: ='IS ,BS Assumptions'!L49/365*M7 -> 5336.577 | N63: ='IS ,BS Assumptions'!M49/365*N7 -> 5733.5636
B64: Current Investments | C64: ='Raw Data'!K44 -> 2011.58 | D64: ='Raw Data'!L44 -> 834.43 | E64: ='Raw Data'!M44 -> 2004.84 | F64: ='Raw Data'!N44 -> 2038.8 | G64: ='Raw Data'!O44 -> 2771.44 | H64: ='Raw Data'!P44 -> 4383.59 | I64: ='Raw Data'!Q44 -> 6849.31 | J64: =I64*1.15 -> 7876.7065 | K64: =J64*1.15 -> 9058.2125 | L64: =K64*1.15 -> 10416.944 | M64: =L64*1.15 -> 11979.486 | N64: =M64*1.15 -> 13776.409
B65: Short-Term Loans & Advances | C65: ='Raw Data'!K48 -> 992.7 | D65: ='Raw Data'!L48 -> 834.5 | E65: ='Raw Data'!M48 -> 904.65 | F65: ='Raw Data'!N48 -> 1376.26 | G65: ='Raw Data'!O48 -> 3143.24 | H65: ='Raw Data'!P48 -> 3714.46 | I65: ='Raw Data'!Q48 -> 3349.67 | J65: =I65*1.05 -> 3517.1535 | K65: =J65*1.05 -> 3693.0112 | L65: =K65*1.05 -> 3877.6617 | M65: =L65*1.05 -> 4071.5448 | N65: =M65*1.05 -> 4275.1221
B66: Other Current Assets | C66: ='Raw Data'!K49+'Raw Data'!K51 -> 262.67 | D66: ='Raw Data'!L49+'Raw Data'!L51 -> 253.43 | E66: ='Raw Data'!M49+'Raw Data'!M51 -> 286.71 | F66: ='Raw Data'!N49+'Raw Data'!N51 -> 310.53 | G66: ='Raw Data'!O49+'Raw Data'!O51 -> 324.14 | H66: ='Raw Data'!P49+'Raw Data'!P51 -> 539.52 | I66: ='Raw Data'!Q49+'Raw Data'!Q51 -> 464.23 | J66: =I66*1.05 -> 487.4415 | K66: =J66*1.05 -> 511.81358 | L66: =K66*1.05 -> 537.40425 | M66: =L66*1.05 -> 564.27447 | N66: =M66*1.05 -> 592.48819
B67: Cash & Cash Equivalents (Balancing Plug) | C67: ='Raw Data'!K47 -> 174.56 | D67: ='Raw Data'!L47 -> 523.07 | E67: ='Raw Data'!M47 -> 874.8 | F67: ='Raw Data'!N47 -> 1428.03 | G67: ='Raw Data'!O47 -> 966.46 | H67: ='Raw Data'!P47 -> 333.2 | I67: ='Raw Data'!Q47 -> 278.45 | J67: =J52-J60-J62-J63-J64-J65-J66 -> -3418.1364 | K67: =K52-K60-K62-K63-K64-K65-K66 -> -6576.9998 | L67: =L52-L60-L62-L63-L64-L65-L66 -> -10159.513 | M67: =M52-M60-M62-M63-M64-M65-M66 -> -14126.762 | N67: =N52-N60-N62-N63-N64-N65-N66 -> -18500.378
B68: Total Current Assets | C68: ='Raw Data'!K50 -> 9478.65 | D68: ='Raw Data'!L50 -> 9027.06 | E68: ='Raw Data'!M50 -> 10192.18 | F68: ='Raw Data'!N50 -> 11335.04 | G68: ='Raw Data'!O50 -> 13371.13 | H68: ='Raw Data'!P50 -> 14857.84 | I68: ='Raw Data'!Q50 -> 18369.22 | J68: =J62+J63+J64+J67+J65+J66 -> 17892.68 | K68: =K62+K63+K64+K67+K65+K66 -> 16776.479 | L68: =L62+L63+L64+L67+L65+L66 -> 15345.1 | M68: =M62+M63+M64+M67+M65+M66 -> 13656.986 | N68: =N62+N63+N64+N67+N65+N66 -> 12010.999
B70: TOTAL ASSETS | C70: ='Raw Data'!K52 -> 18418.81 | D70: ='Raw Data'!L52 -> 20405.66 | E70: ='Raw Data'!M52 -> 22963.74 | F70: ='Raw Data'!N52 -> 25449.05 | G70: ='Raw Data'!O52 -> 27596.47 | H70: ='Raw Data'!P52 -> 31053.23 | I70: ='Raw Data'!Q52 -> 35565.72 | J70: =J60+J68 -> 36019.379 | K70: =K60+K68 -> 36032.004 | L70: =L60+L68 -> 35861.038 | M70: =M60+M68 -> 35581.011 | N70: =N60+N68 -> 35521.055
B73: Cash Flow Statement
B75: Particulars | C75: 2019 Actual | D75: 2020 Actual | E75: 2021 Actual | F75: 2022 Actual | G75: 2023 Actual | H75: 2024 Actual | I75: 2025 Actual | J75: 2026 Forecast | K75: 2027 Forecast | L75: 2028 Forecast | M75: 2029 Forecast | N75: 2030 Forecast
B76: Profit before tax | C76: =C23 -> 2492.83 | D76: =D23 -> 2964.31 | E76: =E23 -> 3207.63 | F76: =F23 -> 3814.77 | G76: =G23 -> 3375.01 | H76: =H23 -> 5310.03 | I76: =I23 -> 6468.82 | J76: =J23 -> 1941.9288 | ... N76: =N23 -> 3302.1961
B77: Add: Depreciation | C77: =C17 -> 569.72 | D77: =D17 -> 599.78 | E77: =E17 -> 468.62 | F77: =F17 -> 460.01 | G77: =G17 -> 595.91 | H77: =H17 -> 587.59 | I77: =I17 -> 573.89 | J77: =J17 -> 704.5056 | ... N77: =N17 -> 761.29694
B78: Add: Finance Cost | C78: =C18 -> 16.97 | D78: =D18 -> 36.05 | E78: =E18 -> 45.07 | F78: =F18 -> 26.93 | G78: =G18 -> 22.27 | H78: =H18 -> 20.25 | I78: =I18 -> 15.11 | J78: =J18 -> 18 | ... N78: =N18 -> 22
B79: Cash Flow before Working Capital Changes | C79: =SUM(C76:C78) -> 3079.52 | D79: =SUM(D76:D78) -> 3600.14 | E79: =SUM(E76:E78) -> 3721.32 | F79: =SUM(F76:F78) -> 4301.71 | G79: =SUM(G76:G78) -> 3993.19 | H79: =SUM(H76:H78) -> 5917.87 | I79: =SUM(I76:I78) -> 7057.82 | J79: =SUM(J76:J78) -> 2664.4344 | ... N79: =SUM(N76:N78) -> 4085.493
B80: Changes in working capital
B81: Inventories | C81: =C62 -> 2868.41 | D81: =D62 -> 3021.36 | E81: =E62 -> 3085.81 | F81: =F62 -> 3485.81 | G81: =G62 -> 3277.36 | H81: =H62 -> 3254.28 | I81: =I62 -> 3607.12 | J81: =J62 -> 4771.7632 | ... N81: =N62 -> 6133.7939
B82: Trade Receivable | C82: =C63 -> 3168.73 | D82: =D63 -> 3560.27 | E82: =E63 -> 3035.37 | F82: =F63 -> 2794.48 | G82: =G63 -> 2888.49 | H82: =H63 -> 2681.75 | I82: =I63 -> 3859.99 | J82: =J63 -> 4657.7514 | ... N82: =N63 -> 5733.5636
B83: Other current assets | C83: =C66 -> 262.67 | D83: =D66 -> 253.43 | E83: =E66 -> 286.71 | F83: =F66 -> 310.53 | G83: =G66 -> 324.14 | H83: =H66 -> 539.52 | I83: =I66 -> 464.23 | J83: =J66 -> 487.4415 | ... N83: =N66 -> 592.48819
B84: Total Current Assets(Operating) | C84: =SUM(C81:C83) -> 6299.81 | D84: =SUM(D81:D83) -> 6835.06 | E84: =SUM(E81:E83) -> 6407.89 | F84: =SUM(F81:F83) -> 6590.82 | G84: =SUM(G81:G83) -> 6489.99 | H84: =SUM(H81:H83) -> 6475.55 | I84: =SUM(I81:I83) -> 7931.34 | J84: =SUM(J81:J83) -> 9916.956 | ... N84: =SUM(N81:N83) -> 12459.846
B85: Trade payable | C85: =C47 -> 1481.35 | D85: =D47 -> 1612.12 | E85: =E47 -> 1495.49 | F85: =F47 -> 1569.73 | G85: =G47 -> 1638.92 | H85: =H47 -> 1684.64 | I85: =I47 -> 1883.71 | J85: =J47 -> 2392.037 | ... N85: =N47 -> 3088.6532
B86: Other current liabilities | C86: =C48 -> 406.59 | D86: =D48 -> 455.04 | E86: =E48 -> 548.66 | F86: =F48 -> 450.3 | G86: =G48 -> 399.52 | H86: =H48 -> 407.08 | I86: =I48 -> 435.65 | J86: =J48 -> 461.789 | ... N86: =N48 -> 582.99797
B87: Provisions | C87: =C49 -> 480.14 | D87: =D49 -> 546.07 | E87: =E49 -> 625.13 | F87: =F49 -> 631.39 | G87: =G49 -> 646.74 | H87: =H49 -> 754.53 | I87: =I49 -> 832.86 | J87: =J49 -> 882.8316 | ... N87: =N49 -> 1114.5546
B88: Total Current Liabalities(Operating) | C88: =SUM(C85:C87) -> 2368.08 | D88: =SUM(D85:D87) -> 2613.23 | E88: =SUM(E85:E87) -> 2669.28 | F88: =SUM(F85:F87) -> 2651.42 | G88: =SUM(G85:G87) -> 2685.18 | H88: =SUM(H85:H87) -> 2846.25 | I88: =SUM(I85:I87) -> 3152.22 | J88: =SUM(J85:J87) -> 3736.6576 | ... N88: =SUM(N85:N87) -> 4786.2058
B89: Net Changes in working capital | C89: =C84-C88 -> 3931.73 | D89: =D84-D88 -> 4221.83 | E89: =E84-E88 -> 3738.61 | F89: =F84-F88 -> 3939.4 | G89: =G84-G88 -> 3804.81 | H89: =H84-H88 -> 3629.3 | I89: =I84-I88 -> 4779.12 | J89: =J84-J88 -> 6180.2985 | ... N89: =N84-N88 -> 7673.64

Sheet PPE Schedule
B1: CIPLA LIMITED – PPE SCHEDULE
B4: Particulars | C4: 2019 Actual | D4: 2020 Actual | E4: 2021 Actual | F4: 2022 Actual | G4: 2023 Actual | H4: 2024 Actual | I4: 2025 Actual | J4: 2026 Forecast | K4: 2027 Forecast | L4: 2028 Forecast | M4: 2029 Forecast | N4: 2030 Forecast
B5: Revenue from Operations (Reference) | C5: ='Financial Statements'!C7 -> 12374.01 | D5: ='Financial Statements'!D7 -> 12659.15 | E5: ='Financial Statements'!E7 -> 11302.71 | F5: ='Financial Statements'!F7 -> 13091.79 | G5: ='Financial Statements'!G7 -> 14345.34 | H5: ='Financial Statements'!H7 -> 16574.34 | I5: ='Financial Statements'!I7 -> 19044.85 | J5: ='Financial Statements'!J7 -> 20568.438 | ... N5: ='Financial Statements'!N7 -> 27983.133
B7: Opening Net PPE (Tangible Assets) | C7: 4212 | D7: ='Financial Statements'!C56 -> 4424.79 | E7: ='Financial Statements'!D56 -> 4344.27 | F7: ='Financial Statements'!E56 -> 4297.77 | G7: ='Financial Statements'!F56 -> 4114.25 | H7: ='Financial Statements'!G56 -> 4251.53 | I7: ='Financial Statements'!H56 -> 4273.41 | J7: =I10 -> 4403.16 | K7: =J10 -> 4459.5682 | L7: =K10 -> 4605.1946 | M7: =L10 -> 4807.0564 | N7: =M10 -> 5075.3129
B8: Capital Expenditure – Actuals from Cash Flow Statement | Forecast = Capex % × Revenue | C8: =-'Raw Data'!B109 -> 312.05 | D8: =-'Raw Data'!C109 -> 449.71 | E8: =-'Raw Data'!D109 -> 516.97 | F8: =-'Raw Data'!E109 -> 331.68 | G8: =-'Raw Data'!F109 -> 684.15 | H8: =-'Raw Data'!G109 -> 682.71 | I8: =-'Raw Data'!H109 -> 728.68 | J8: ='IS ,BS Assumptions'!I52*J5 -> 760.91385 | K8: ='IS ,BS Assumptions'!J52*K5 -> 859.15732 | L8: ='IS ,BS Assumptions'!K52*L5 -> 938.69285 | M8: ='IS ,BS Assumptions'!L52*M5 -> 989.31504 | N8: ='IS ,BS Assumptions'!M52*N5 -> 1119.8186
B9: Less: Depreciation & Amortisation | C9: ='Raw Data'!B71 -> 569.72 | D9: ='Raw Data'!C71 -> 599.78 | E9: ='Raw Data'!D71 -> 468.62 | F9: ='Raw Data'!E71 -> 460.01 | G9: ='Raw Data'!F71 -> 595.91 | H9: ='Raw Data'!G71 -> 587.59 | I9: ='Raw Data'!H71 -> 573.89 | J9: =J7*J11 -> 704.5056 | K9: =K7*K11 -> 713.53092 | L9: =L7*L11 -> 736.83114 | M9: =M7*M11 -> 721.05845 | N9: =N7*N11 -> 761.29694
B10: Closing Net PPE (Tangible) | C10: ='Financial Statements'!C56 -> 4424.79 | D10: ='Financial Statements'!D56 -> 4344.27 | E10: ='Financial Statements'!E56 -> 4297.77 | F10: ='Financial Statements'!F56 -> 4114.25 | G10: ='Financial Statements'!G56 -> 4251.53 | H10: ='Financial Statements'!H56 -> 4273.41 | I10: ='Financial Statements'!I56 -> 4403.16 | J10: =J7+J8-J9 -> 4459.5682 | K10: =K7+K8-K9 -> 4605.1946 | L10: =L7+L8-L9 -> 4807.0564 | M10: =M7+M8-M9 -> 5075.3129 | N10: =N7+N8-N9 -> 5433.8346
B11: Depreciation Rate % of Opening PPE | C11: N/A | D11: ='Raw Data'!C71/'Raw Data'!B31 -> 2.2639188 | E11: ='Raw Data'!D71/'Raw Data'!C31 -> 1.8453239 | F11: ='Raw Data'!E71/'Raw Data'!D31 -> 1.9609941 | G11: ='Raw Data'!F71/'Raw Data'!E31 -> 2.4069392 | H11: ='Raw Data'!G71/'Raw Data'!F31 -> 2.2857198 | I11: ='Raw Data'!H71/'Raw Data'!G31 -> 2.1125304 | J11: 0.16 | K11: 0.16 | L11: 0.16 | M11: 0.15 | N11: 0.15
B12: Forecast Depreciation - Linked to Assumptions Sheet | J12: =J9 -> 704.5056 | K12: =K9 -> 713.53092 | L12: =L9 -> 736.83114 | M12: =M9 -> 721.05845 | N12: =N9 -> 761.29694
B13: Capex % of Revenue (Computed) | C13: =C8/C5 -> 0.025218179 | D13: =D8/D5 -> 0.035524502 | E13: =E8/E5 -> 0.045738588 | F13: =F8/F5 -> 0.025334962 | G13: =G8/G5 -> 0.047691445 | H13: =H8/H5 -> 0.04119078 | I13: =I8/I5 -> 0.038261262 | J13: =J8/J5 -> 0.036994246 | ... N13: =N8/N5 -> 0.040017629

Sheet Beta
A1: BETA CALCULATION
A3: CIPLA LTD. | E3: BSE SENSEX | I3: BETA : Market Risk
A4: Date | B4: Close Price | C4: Return % | E4: Date | F4: SENSEX | G4: Return % | I4: 10 Year Beta Computation
A5: 42370 | B5: 654.7 | E5: 42370 | F5: 26160.9
A6: 42373 | B6: 645.55 | C6: =LN(B6/B5) -> -0.014074449 | E6: 42373 | F6: 25623.35 | G6: =LN(F6/F5) -> -0.020761885 | I6: Using SLOPE Function | J6: =SLOPE(C6:C2482,G6:G2482) -> 0.44183817
A7: 42374 | B7: 641.15 | C7: =LN(B7/B6) -> -0.0068392277 | E7: 42374 | F7: 25580.34 | G7: =LN(F7/F6) -> -0.0016799574
A8: 42375 | B8: 652.4 | C8: =LN(B8/B7) -> 0.017394432 | E8: 42375 | F8: 25406.33 | G8: =LN(F8/F7) -> -0.0068257321
A9: 42376 | B9: 639.15 | C9: =LN(B9/B8) -> -0.020518702 | E9: 42376 | F9: 24851.83 | G9: =LN(F9/F8) -> -0.022066964
A10: 42377 | B10: 622.45 | C10: =LN(B10/B9) -> -0.026475865 | E10: 42377 | F10: 24934.33 | G10: =LN(F10/F9) -> 0.0033141771 | I10: Performance VS Market
A11: 42380 | B11: 610.25 | C11: =LN(B11/B10) -> -0.019794595 | E11: 42380 | F11: 24825.04 | G11: =LN(F11/F10) -> -0.0043927476
A12: 42381 | B12: 611.65 | C12: =LN(B12/B11) -> 0.0022915142 | E12: 42381 | F12: 24682.03 | G12: =LN(F12/F11) -> -0.0057773727 | I12: Cipla Ltd. | J12: =AVERAGE(C6:C2482) -> 0.00033761957
A13: 42382 | B13: 608.7 | C13: =LN(B13/B12) -> -0.004834688 | E13: 42382 | F13: 24854.11 | G13: =LN(F13/F12) -> 0.0069476827 | I13: BSE Sensex | J13: =AVERAGE(G6:G2482) -> 0.00047677725
A14: 42383 | B14: 613.9 | C14: =LN(B14/B13) -> 0.0085065129 | E14: 42383 | F14: 24772.97 | G14: =LN(F14/F13) -> -0.0032699918
A15: 42384 | B15: 607.4 | C15: =LN(B15/B14) -> -0.010644496 | E15: 42384 | F15: 24455.04 | G15: =LN(F15/F14) -> -0.01291681
A16: 42387 | B16: 590.85 | C16: =LN(B16/B15) -> -0.027625375 | E16: 42387 | F16: 24188.37 | G16: =LN(F16/F15) -> -0.010964391
A17: 42388 | B17: 597.1 | C17: =LN(B17/B16) -> 0.010522425 | E17: 42388 | F17: 24479.84 | G17: =LN(F17/F16) -> 0.011977983
A18: 42389 | B18: 593.5 | C18: =LN(B18/B17) -> -0.0060473895 | E18: 42389 | F18: 24062.04 | G18: =LN(F18/F17) -> -0.017214427
A19: 42390 | B19: 581.65 | C19: =LN(B19/B18) -> -0.020168322 | E19: 42390 | F19: 23962.21 | G19: =LN(F19/F18) -> -0.0041574889
A20: 42391 | B20: 583.35 | C20: =LN(B20/B19) -> 0.002918457 | E20: 42391 | F20: 24435.66 | G20: =LN(F20/F19) -> 0.019565535
A21: 42394 | B21: 581.5 | C21: =LN(B21/B20) -> -0.0031763773 | E21: 42394 | F21: 24485.95 | G21: =LN(F21/F20) -> 0.0020559429
A22: 42396 | B22: 580.5 | C22: =LN(B22/B21) -> -0.0017211708 | E22: 42396 | F22: 24492.39 | G22: =LN(F22/F21) -> 0.00026297339
A23: 42397 | B23: 578 | C23: =LN(B23/B22) -> -0.0043159325 | E23: 42397 | F23: 24469.57 | G23: =LN(F23/F22) -> -0.00093215229
A24: 42398 | B24: 585.7 | C24: =LN(B24/B23) -> 0.013233844 | E24: 42398 | F24: 24870.69 | G24: =LN(F24/F23) -> 0.016259697
A25: 42401 | B25: 597.8 | C25: =LN(B25/B24) -> 0.020448537 | E25: 42401 | F25: 24824.83 | G25: =LN(F25/F24) -> -0.0018456397
... A2482: 46022 | B2482: 1510.9 | C2482: =LN(B2482/B2481) -> 0.012990224 | E2482: 46022 | F2482: 85220.6 | G2482: =LN(F2482/F2481) -> 0.0064218452

Sheet WACC
A1: Weighted Average Cost of Capital
A4: Capital Structure
A5: Total Debt | B5: ='Financial Statements'!I41 -> 86.18
A6: Total Equity | B6: ='Financial Statements'!I38 -> 32099.24
A7: Total Mix | B7: =SUM(B5:B6) -> 32185.42
A8: % of debt | B8: =B5/B7 -> 0.0026776099
A9: % of Equity | B9: =B6/B7 -> 0.99732239
A10: Debt to Equity | B10: =B5/B6 -> 0.0026847988
A12: Cost Of Equity
A13: Risk Free Rate(Rf) | B13: =Sources!C7 -> 0.0667
A14: Beta | B14: =Beta!J6 -> 0.44183817
A15: Market Risk Premium | B15: =Sources!C9 -> 0.060931297
A16: Cost Of Equity | B16: =B13+B14*B15 -> 0.093621773
A18: Cost Of Debt
A19: Cost Of Debt | B19: ='Financial Statements'!I18/'Financial Statements'!I41 -> 0.1753307
A20: Tax Rate | B20: =Sources!C6 -> 0.2362
A21: Cost Of Debt after tax | B21: =B19*(1-B20) -> 0.13391759
A23: WACC
A24: Source | B24: Weight | C24: Cost | D24: Weighted Cost
A25: Debt | B25: =B8 -> 0.0026776099 | C25: =B21 -> 0.13391759 | D25: =B25*C25 -> 0.00035857907
A26: Equity | B26: =B9 -> 0.99732239 | C26: =B16 -> 0.093621773 | D26: =B26*C26 -> 0.09337109
A27: WACC | D27: =SUM(D25:D26) -> 0.093729669

Sheet EVA
A1: EVA = NOPAT -( WACC* Invested Capital)
A3: NOPAT = Operating Profit* (1 - Tax Rate)
B4: 2019 | C4: 2020 | D4: 2021 | E4: 2022 | F4: 2023 | G4: 2024 | H4: 2025
A5: Operating Profit | B5: ='Financial Statements'!C20 -> 961.35 | C5: ='Financial Statements'!D20 -> 1037.03 | D5: ='Financial Statements'!E20 -> 939.38 | E5: ='Financial Statements'!F20 -> -80.45 | F5: ='Financial Statements'!G20 -> 1004.12 | G5: ='Financial Statements'!H20 -> 2398.37 | H5: ='Financial Statements'!I20 -> 3396.81
A6: Tax rate | B6: =Sources!$C$6 -> 0.2362 | C6: =Sources!$C$6 -> 0.2362 | D6: =Sources!$C$6 -> 0.2362 | E6: =Sources!$C$6 -> 0.2362 | F6: =Sources!$C$6 -> 0.2362 | G6: =Sources!$C$6 -> 0.2362 | H6: =Sources!$C$6 -> 0.2362
A7: NOPAT | B7: =B5*(1-B6) -> 734.27913 | C7: =C5*(1-C6) -> 792.08351 | D7: =D5*(1-D6) -> 717.49844 | E7: =E5*(1-E6) -> -61.44771 | F7: =F5*(1-F6) -> 766.94686 | G7: =G5*(1-G6) -> 1831.875 | H7: =H5*(1-H6) -> 2594.4835
A9: Capital Employed = Total Shareholders' Funds+ Total Debt
B10: 2019 | C10: 2020 | D10: 202 | E10: 2022 | F10: 2023 | G10: 2024 | H10: 2025
A11: Total Equity (M) | B11: ='Financial Statements'!C38 -> 15781.91 | C11: ='Financial Statements'!D38 -> 17402.96 | D11: ='Financial Statements'!E38 -> 19927.56 | E11: ='Financial Statements'!F38 -> 22513.55 | F11: ='Financial Statements'!G38 -> 24638.09 | G11: ='Financial Statements'!H38 -> 27973.92 | H11: ='Financial Statements'!I38 -> 32099.24
A12: Total Debt (M) | B12: ='Financial Statements'!C40+'Financial Statements'!C41 -> 0 | C12: ='Financial Statements'!D40+'Financial Statements'!D41 -> 0 | D12: ='Financial Statements'!E40+'Financial Statements'!E41 -> 29.46 | E12: ='Financial Statements'!F40+'Financial Statements'!F41 -> 15.53 | F12: ='Financial Statements'!G40+'Financial Statements'!G41 -> 35.53 | G12: ='Financial Statements'!H40+'Financial Statements'!H41 -> 29.55 | H12: ='Financial Statements'!I40+'Financial Statements'!I41 -> 86.18
A13: Capital Employed | B13: 4841010 | C13: 4841011 | D13: 4841012 | E13: 4841013 | F13: 4841014 | G13: 4841015 | H13: 4841016
A15: WACC= Ke*Re+ Kd*Rd(1-tax rate)
A17: Cost of Equity (Ke)=Rf+Beta(Rm-Rf)
A18: Rf | B18: =Sources!C7 -> 0.0667
A19: Beta | B19: =Beta!J6 -> 0.44183817
A20: ERP | B20: =Sources!C9 -> 0.060931297
A21: Ke | B21: =WACC!B16 -> 0.093621773
A22: Kd | B22: =WACC!B21 -> 0.13391759
B24: 2019 | C24: 2020 | D24: 202 | E24: 2022 | F24: 2023 | G24: 2024 | H24: 2025
A25: Equity | B25: =B11 -> 15781.91 | C25: =C11 -> 17402.96 | D25: =D11 -> 19927.56 | E25: =E11 -> 22513.55 | F25: =F11 -> 24638.09 | G25: =G11 -> 27973.92 | H25: =H11 -> 32099.24
A26: Debt | B26: =B12 -> 0 | C26: =C12 -> 0 | D26: =D12 -> 29.46 | E26: =E12 -> 15.53 | F26: =F12 -> 35.53 | G26: =G12 -> 29.55 | H26: =H12 -> 86.18
A27: Equity+Debt | B27: =B25+B26 -> 15781.91 | C27: =C25+C26 -> 17402.96 | D27: =D25+D26 -> 19957.02 | E27: =E25+E26 -> 22529.08 | F27: =F25+F26 -> 24673.62 | G27: =G25+G26 -> 28003.47 | H27: =H25+H26 -> 32185.42
A28: E/V | B28: =B25/B27 -> 1 | C28: =C25/C27 -> 1 | D28: =D25/D27 -> 0.99852383 | E28: =E25/E27 -> 0.99931067 | F28: =F25/F27 -> 0.99856 | G28: =G25/G27 -> 0.99894477 | H28: =H25/H27 -> 0.99732239
A29: D/V | B29: =B26/B27 -> 0 | C29: =C26/C27 -> 0 | D29: =D26/D27 -> 0.0014761723 | E29: =E26/E27 -> 0.0006893313 | F29: =F26/F27 -> 0.0014399995 | G29: =G26/G27 -> 0.0010552264 | H29: =H26/H27 -> 0.0026776099
A30: WACC | B30: =(B28*$B$21)+(B29*$B$22) -> 0.093621773 | C30: =(C28*$B$21)+(C29*$B$22) -> 0.093621773 | D30: =(D28*$B$21)+(D29*$B$22) -> 0.093681256 | E30: =(E28*$B$21)+(E29*$B$22) -> 0.09364955 | F30: =(F28*$B$21)+(F29*$B$22) -> 0.093679799 | G30: =(G28*$B$21)+(G29*$B$22) -> 0.093664294 | H30: =(H28*$B$21)+(H29*$B$22) -> 0.093729669
A32: EVA | B32: =B7-(B30*B13) -> -452489.66 | C32: =C7-(C30*C13) -> -452431.95 | D32: =D7-(D30*D13) -> -452794.59 | E32: =E7-(E30*E13) -> -453420.14 | F32: =F7-(F30*F13) -> -452738.27 | G32: =G7-(G30*G13) -> -451598.38 | H32: =H7-(H30*H13) -> -451152.35

Sheet DCF Valuation
A1: DCF Valuation
A4: Assumtions/Base
A5: Tax Rate | B5: =Sources!C6 -> 0.2362
A6: Discount Rate (WACC) | B6: =WACC!D27 -> 0.093729669
A7: Perpetural Growth Rate | B7: =Sources!C10 -> 0.06
A8: Valuation Date | B8: 46112
A9: Last Fiscal Year End | B9: 45747
A10: Current Market Price | B10: =Sources!C13 -> 1242.65
A11: Total Shares Outstanding (in Cr.) | B11: ='Financial Statements'!I36 -> 161.52
A12: Debt (in Cr.) | B12: =WACC!B5 -> 86.18
A13: Cash (in Cr.) | B13: ='Financial Statements'!I67 -> 278.45
G17: INR Cr.
A18: Discounted Cash Flows
A19: YEARS | B19: 1 | C19: 2 | D19: 3 | E19: 4 | F19: 5 | G19: Growth | J19: INTRINSIC VALUE
A20: Particulars | B20: 2026 | C20: 2027 | D20: 2028 | E20: 2029 | F20: 2030 | G20: Terminal Value | J20: PV of Cash Flows | K20: =B31+C31+D31+E31+F31 -> 4089.9937
A21: EBIT | B21: ='Financial Statements'!J20 -> 1959.9288 | C21: ='Financial Statements'!K20 -> 2182.4869 | D21: ='Financial Statements'!L20 -> 2394.5387 | E21: ='Financial Statements'!M20 -> 2682.8471 | F21: ='Financial Statements'!N20 -> 3324.1961 | J21: Continuing Value | K21: =G27 -> 54914.212
A22: Tax Rate | B22: =$B$5 -> 0.2362 | C22: =$B$5 -> 0.2362 | D22: =$B$5 -> 0.2362 | E22: =$B$5 -> 0.2362 | F22: =$B$5 -> 0.2362 | J22: PV of contuning value | K22: =G31 -> 35086.075
A23: NOPAT | B23: =B21*(1-B22) -> 1496.9936 | C23: =C21*(1-C22) -> 1666.9835 | D23: =D21*(1-D22) -> 1828.9486 | E23: =E21*(1-E22) -> 2049.1586 | F23: =F21*(1-F22) -> 2539.021 | J23: Enterprise Value (in Cr) | K23: =K22+K20 -> 39176.069
A24: Add- Depreciation | B24: ='PPE Schedule'!J12 -> 704.5056 | C24: ='PPE Schedule'!K12 -> 713.53092 | D24: ='PPE Schedule'!L12 -> 736.83114 | E24: ='PPE Schedule'!M12 -> 721.05845 | F24: ='PPE Schedule'!N12 -> 761.29694 | J24: Less: Debt (in Cr) | K24: =B12 -> 86.18
A25: Less-Capex | B25: ='PPE Schedule'!J8 -> 760.91385 | C25: ='PPE Schedule'!K8 -> 859.15732 | D25: ='PPE Schedule'!L8 -> 938.69285 | E25: ='PPE Schedule'!M8 -> 989.31504 | F25: ='PPE Schedule'!N8 -> 1119.8186 | J25: Add: Cash (in Cr) | K25: =B13 -> 278.45
A26: Less-Net Changes In WC | B26: ='Financial Statements'!J89-'Financial Statements'!I89 -> 1401.1785 | C26: ='Financial Statements'!K89-'Financial Statements'!J89 -> 424.10566 | D26: ='Financial Statements'!L89-'Financial Statements'!K89 -> 355.98069 | E26: ='Financial Statements'!M89-'Financial Statements'!L89 -> 280.15042 | F26: ='Financial Statements'!N89-'Financial Statements'!M89 -> 433.10473 | J26: Equity Value (in Cr) | K26: =K23-K24+K25 -> 39368.339
A27: Free Cash Flows | B27: =B23+B24-B25-B26 -> 39.406875 | C27: =C23+C24-C25-C26 -> 1097.2514 | D27: =D23+D24-D25-D26 -> 1271.1062 | E27: =E23+E24-E25-E26 -> 1500.7516 | F27: =F23+F24-F25-F26 -> 1747.3946 | G27: =F27*(1+G29)/(G28-G29) -> 54914.212 | J27: No. of share (in Cr.) | K27: =B11 -> 161.52
A28: WACC | B28: =$B$6 -> 0.093729669 | C28: =$B$6 -> 0.093729669 | D28: =$B$6 -> 0.093729669 | E28: =$B$6 -> 0.093729669 | F28: =$B$6 -> 0.093729669 | G28: =$B$6 -> 0.093729669 | J28: Intrincsic value of share | K28: =K26/K27 -> 243.73662
A29: Growth | F29: =B7 -> 0.06 | G29: =B7 -> 0.06 | J29: Current share price | K29: =B10 -> 1242.65
A30: Discounting Factor | B30: =1/(1+B28)^B19 -> 0.91430271 | C30: =1/(1+C28)^C19 -> 0.83594944 | D30: =1/(1+D28)^D19 -> 0.76431084 | E30: =1/(1+E28)^E19 -> 0.69881147 | F30: =1/(1+F28)^F19 -> 0.63892522 | G30: =1/(1+G28)^F19 -> 0.63892522 | J30: No of shares | K30: =B11 -> 161.52
A31: PV of Free Cash Flow | B31: =B27*B30 -> 36.029812 | C31: =C27*C30 -> 917.24674 | D31: =D27*D30 -> 971.52028 | E31: =E27*E30 -> 1048.7425 | F31: =F27*F30 -> 1116.4545 | G31: =G30*G27 -> 35086.075 | J31: Market capitalization (in Cr) | K31: =K30*K29 -> 200712.83
A34: Market Value vs Fair Value
A35: CMP | B35: =B10 -> 1242.65 | E35: WACC → | F35: =K28 -> 243.73662 | G35: 0.1 | H35: 0.11 | I35: 0.12 | J35: 0.13 | K35: 0.14
A36: Upside Potential | B36: =B37-B35 -> -998.91338 | E36: g ↓ | F36: 0.04 | G36: 142.43756 | H36: 120.60485 | I36: 104.27155 | J36: 91.603011 | K36: 81.498522
A37: Fair Value | B37: =K28 -> 243.73662 | F37: 0.05 | G37: 167.06803 | H37: 137.57257 | I37: 116.54889 | J37: 100.8185 | K37: 88.615617
A38: Upside Potential % | B38: =B36/B35 -> -0.80385738 | F38: 0.06 | G38: 204.01373 | H38: 161.32737 | I38: 132.91869 | J38: 112.66699 | K38: 97.511985
A39: Nature | B39: Over valued | F39: 0.07 | G39: 265.5899 | H39: 196.95958 | I39: 155.83641 | J39: 128.46497 | K39: 108.95017
A40: Recommendation | B40: Sell / Avoid | F40: 0.08 | G40: 388.74225 | H40: 256.3466 | I40: 190.21298 | J40: 150.58214 | K40: 124.20109

Sheet Relative Valuation
A1: RELATIVE VALUATION
A3: Company | B3: Market Data | F3: Financial Data | J3: Valuation Ratios
A4: Company | B4: Price (₹) | C4: No. of Shares (in Cr.) | D4: Market Cap (in Cr) | E4: Enterprise Value (in Cr) | F4: Sales (in Cr) | G4: EBITDA (in Cr) | H4: EBIT (in Cr) | I4: EPS (₹) | J4: P/E | K4: EV/Sales | L4: EV/EBITDA | M4: EV/EBIT | N4: Net Debt (in Cr) | O4: D&A (in Cr)
A5: Sun Pharma | B5: 1744 | C5: 239.93 | D5: =B5*C5 -> 418437.92 | E5: =D5+N5 -> 402637.92 | F5: 55370 | G5: 17112 | H5: =G5-O5 -> 13280 | I5: 45.9 | J5: =B5/I5 -> 37.995643 | K5: =E5/F5 -> 7.2717703 | L5: =E5/G5 -> 23.529565 | M5: =E5/H5 -> 30.31912 | N5: -15800 | O5: 3832
A6: Zydus | B6: 871 | C6: 100.63 | D6: =B6*C6 -> 87648.73 | E6: =D6+N6 -> 84448.73 | F6: 22950 | G6: 6311 | H6: =G6-O6 -> 4980 | I6: 49 | J6: =B6/I6 -> 17.77551 | K6: 3.6796832 | L6: 13.381196 | M6: 16.957576 | N6: -3200 | O6: 1331
A7: Dr. Reddy's | B7: 1214 | C7: 83.24 | D7: =B7*C7 -> 101053.36 | E7: =D7+N7 -> 95653.36 | F7: 32380 | G7: 9131 | H7: =G7-O7 -> 7260 | I7: 53 | J7: =B7/I7 -> 22.90566 | K7: 2.9540877 | L7: 10.475672 | M7: 13.175394 | N7: -5400 | O7: 1871
A8: Lupin | B8: 2290 | C8: 45.72 | D8: =B8*C8 -> 104698.8 | E8: =D8+N8 -> 105898.8 | F8: 22708 | G8: 5609 | H8: =G8-O8 -> 4440 | I8: 71.7 | J8: =B8/I8 -> 31.938633 | K8: 4.6635018 | L8: 18.880157 | M8: 23.851081 | N8: 1200 | O8: 1169
A10: Average Data | J10: =AVERAGE(J5:J8) -> 27.653862 | K10: =AVERAGE(K5:K8) -> 4.6422608 | L10: =AVERAGE(L5:L8) -> 16.566648 | M10: =AVERAGE(M5:M8) -> 21.075793
A11: Median Data | J11: =MEDIAN(J5:J8) -> 27.422147 | K11: =MEDIAN(K5:K8) -> 4.1715925 | L11: =MEDIAN(L5:L8) -> 16.130677 | M11: =MEDIAN(M5:M8) -> 20.404329

Sheet All Ratios Forecast
A1: RATIOS
A3: Growth | B3: 2019 Actual | C3: 2020 Actual | D3: 2021 Actual | E3: 2022 Actual | F3: 2023 Actual | G3: 2024 Actual | H3: 2025 Actual | I3: 2026 Forecast | J3: 2027 Forecast | K3: 2028 Forecast | L3: 2029 Forecast | M3: 2030 Forecast
A4: Operating Income (%) | B4: =('Financial Statements'!D20-'Financial Statements'!C20)/'Financial Statements'!C20 -> 0.07872263 | C4: =('Financial Statements'!E20-'Financial Statements'!D20)/'Financial Statements'!D20 -> -0.094163139 | D4: =('Financial Statements'!F20-'Financial Statements'!E20)/'Financial Statements'!E20 -> -1.0856416 | E4: =('Financial Statements'!G20-'Financial Statements'!F20)/'Financial Statements'!F20 -> -13.481293 | F4: =('Financial Statements'!H20-'Financial Statements'!G20)/'Financial Statements'!G20 -> 1.3885293 | G4: =('Financial Statements'!I20-'Financial Statements'!H20)/'Financial Statements'!H20 -> 0.4162994 | H4: =('Financial Statements'!J20-'Financial Statements'!I20)/'Financial Statements'!I20 -> -0.42300901 | I4: =('Financial Statements'!K20-'Financial Statements'!J20)/'Financial Statements'!J20 -> 0.11355421 | ... M4: =('Financial Statements'!O20-'Financial Statements'!N20)/'Financial Statements'!N20 -> -1
A5: EBITDA (%) | B5: =('Financial Statements'!D14-'Financial Statements'!C14)/'Financial Statements'!C14 -> 0.069062812 | C5: =('Financial Statements'!E14-'Financial Statements'!D14)/'Financial Statements'!D14 -> -0.1397902 | D5: =('Financial Statements'!F14-'Financial Statements'!E14)/'Financial Statements'!E14 -> -0.73042614 | E5: =('Financial Statements'!G14-'Financial Statements'!F14)/'Financial Statements'!F14 -> 3.2154864 | F5: =('Financial Statements'!H14-'Financial Statements'!G14)/'Financial Statements'!G14 -> 0.86619001 | G5: =('Financial Statements'!I14-'Financial Statements'!H14)/'Financial Statements'!H14 -> 0.32979008 | H5: =('Financial Statements'!J14-'Financial Statements'!I14)/'Financial Statements'!I14 -> -0.32897616 | I5: =('Financial Statements'!K14-'Financial Statements'!J14)/'Financial Statements'!J14 -> 0.086916562 | ... M5: =('Financial Statements'!O14-'Financial Statements'!N14)/'Financial Statements'!N14 -> -1
A6: Adj PAT (%) | B6: =('Financial Statements'!D25-'Financial Statements'!C25)/'Financial Statements'!C25 -> 0.2275777 | C6: =('Financial Statements'!E25-'Financial Statements'!D25)/'Financial Statements'!D25 -> 0.064753663 | D6: =('Financial Statements'!F25-'Financial Statements'!E25)/'Financial Statements'!E25 -> 0.19837701 | E6: =('Financial Statements'!G25-'Financial Statements'!F25)/'Financial Statements'!F25 -> -0.15026049 | F6: =('Financial Statements'!H25-'Financial Statements'!G25)/'Financial Statements'!G25 -> 0.6221598 | G6: =('Financial Statements'!I25-'Financial Statements'!H25)/'Financial Statements'!H25 -> 0.26498252 | H6: =('Financial Statements'!J25-'Financial Statements'!I25)/'Financial Statements'!I25 -> -0.7091275 | I6: =('Financial Statements'!K25-'Financial Statements'!J25)/'Financial Statements'!J25 -> 0.11538496 | ... M6: =('Financial Statements'!O25-'Financial Statements'!N25)/'Financial Statements'!N25 -> -1
A7: Adj EPS (%) | B7: =('Financial Statements'!D28-'Financial Statements'!C28)/'Financial Statements'!C28 -> 0.22653584 | C7: =('Financial Statements'!E28-'Financial Statements'!D28)/'Financial Statements'!D28 -> 0.064695652 | D7: =('Financial Statements'!F28-'Financial Statements'!E28)/'Financial Statements'!E28 -> 0.19764783 | E7: =('Financial Statements'!G28-'Financial Statements'!F28)/'Financial Statements'!F28 -> -0.15057283 | F7: =('Financial Statements'!H28-'Financial Statements'!G28)/'Financial Statements'!G28 -> 0.62170841 | G7: =('Financial Statements'!I28-'Financial Statements'!H28)/'Financial Statements'!H28 -> 0.26455446 | H7: =('Financial Statements'!J28-'Financial Statements'!I28)/'Financial Statements'!I28 -> -0.70889338 | I7: =('Financial Statements'!K28-'Financial Statements'!J28)/'Financial Statements'!J28 -> 0.11538496 | ... M7: =('Financial Statements'!O28-'Financial Statements'!N28)/'Financial Statements'!N28 -> -1
A9: Profitability | B9: 2019 Actual | C9: 2020 Actual | D9: 2021 Actual | E9: 2022 Actual | F9: 2023 Actual | G9: 2024 Actual | H9: 2025 Actual | I9: 2026 Forecast | J9: 2027 Forecast | K9: 2028 Forecast | L9: 2029 Forecast | M9: 2030 Forecast
A10: EBITDA Margin (%) | B10: =('Financial Statements'!C14/'Financial Statements'!C7) -> 0.12373273 | C10: =('Financial Statements'!D14/'Financial Statements'!D7) -> 0.12929857 | D10: =('Financial Statements'!E14/'Financial Statements'!E7) -> 0.12457189 | E10: =('Financial Statements'!F14/'Financial Statements'!F7) -> 0.028992216 | F10: =('Financial Statements'!G14/'Financial Statements'!G7) -> 0.11153657 | G10: =('Financial Statements'!H14/'Financial Statements'!H7) -> 0.18015559 | H10: =('Financial Statements'!I14/'Financial Statements'!I7) -> 0.20849206 | I10: =('Financial Statements'!J14/'Financial Statements'!J7) -> 0.12953995 | ... M10: =('Financial Statements'!N14/'Financial Statements'!N7) -> 0.14599841
A11: Operating Income | B11: ='Financial Statements'!C20 -> 961.35 | C11: ='Financial Statements'!D20 -> 1037.03 | D11: ='Financial Statements'!E20 -> 939.38 | E11: ='Financial Statements'!F20 -> -80.45 | F11: ='Financial Statements'!G20 -> 1004.12 | G11: ='Financial Statements'!H20 -> 2398.37 | H11: ='Financial Statements'!I20 -> 3396.81 | I11: ='Financial Statements'!J20 -> 1959.9288 | ... M11: ='Financial Statements'!N20 -> 3324.1961
A12: EBIT Margin (%) | B12: ='Financial Statements'!C20/'Financial Statements'!C7 -> 0.077691064 | C12: ='Financial Statements'!D20/'Financial Statements'!D7 -> 0.081919402 | D12: ='Financial Statements'!E20/'Financial Statements'!E7 -> 0.083111042 | E12: ='Financial Statements'!F20/'Financial Statements'!F7 -> -0.0061450726 | F12: ='Financial Statements'!G20/'Financial Statements'!G7 -> 0.06999625 | G12: ='Financial Statements'!H20/'Financial Statements'!H7 -> 0.1447038 | H12: ='Financial Statements'!I20/'Financial Statements'!I7 -> 0.17835845 | I12: ='Financial Statements'!J20/'Financial Statements'!J7 -> 0.095288167 | ... M12: ='Financial Statements'!N20/'Financial Statements'!N7 -> 0.11879285
A13: PAT | B13: ='Financial Statements'!C25 -> 1888.41 | C13: ='Financial Statements'!D25 -> 2318.17 | D13: ='Financial Statements'!E25 -> 2468.28 | E13: ='Financial Statements'!F25 -> 2957.93 | F13: ='Financial Statements'!G25 -> 2513.47 | G13: ='Financial Statements'!H25 -> 4077.25 | H13: ='Financial Statements'!I25 -> 5157.65 | I13: ='Financial Statements'!J25 -> 1500.2186 | ... M13: ='Financial Statements'!N25 -> 2533.9679
A14: PAT Margin (%) | B14: ='Financial Statements'!C25/'Financial Statements'!C7 -> 0.152611 | C14: ='Financial Statements'!D25/'Financial Statements'!D7 -> 0.18312209 | D14: ='Financial Statements'!E25/'Financial Statements'!E7 -> 0.21837949 | E14: ='Financial Statements'!F25/'Financial Statements'!F7 -> 0.22593778 | F14: ='Financial Statements'!G25/'Financial Statements'!G7 -> 0.1752116 | G14: ='Financial Statements'!H25/'Financial Statements'!H7 -> 0.24599773 | H14: ='Financial Statements'!I25/'Financial Statements'!I7 -> 0.27081599 | I14: ='Financial Statements'!J25/'Financial Statements'!J7 -> 0.072937894 | ... M14: ='Financial Statements'!N25/'Financial Statements'!N7 -> 0.090553404
A15: ROE (%) | B15: ='Financial Statements'!C25/'Financial Statements'!C38 -> 0.11965662 | C15: ='Financial Statements'!D25/'Financial Statements'!D38 -> 0.1332055 | D15: ='Financial Statements'!E25/'Financial Statements'!E38 -> 0.12386263 | E15: ='Financial Statements'!F25/'Financial Statements'!F38 -> 0.13138443 | F15: ='Financial Statements'!G25/'Financial Statements'!G38 -> 0.10201562 | G15: ='Financial Statements'!H25/'Financial Statements'!H38 -> 0.14575183 | H15: ='Financial Statements'!I25/'Financial Statements'!I38 -> 0.16067826 | I15: ='Financial Statements'!J25/'Financial Statements'!J38 -> 0.04690307 | ... M15: ='Financial Statements'!N25/'Financial Statements'!N38 -> 0.083426698
A16: ROCE (%) | B16: ='Financial Statements'!C20/('Financial Statements'!C70-'Financial Statements'!C44) -> 0.052966971 | C16: ='Financial Statements'!D20/('Financial Statements'!D70-'Financial Statements'!D44) -> 0.051793879 | D16: ='Financial Statements'!E20/('Financial Statements'!E70-'Financial Statements'!E44) -> 0.041529654 | E16: ='Financial Statements'!F20/('Financial Statements'!F70-'Financial Statements'!F44) -> -0.0031958984 | F16: ='Financial Statements'!G20/('Financial Statements'!G70-'Financial Statements'!G44) -> 0.036730055 | G16: ='Financial Statements'!H20/('Financial Statements'!H70-'Financial Statements'!H44) -> 0.077777817 | H16: ='Financial Statements'!I20/('Financial Statements'!I70-'Financial Statements'!I44) -> 0.096274204 | I16: ='Financial Statements'!J20/('Financial Statements'!J70-'Financial Statements'!J44) -> 0.054865899 | ... M16: ='Financial Statements'!N20/('Financial Statements'!N70-'Financial Statements'!N44) -> 0.094545388
A18: Valuations | B18: 2019 Actual | C18: 2020 Actual | D18: 2021 Actual | E18: 2022 Actual | F18: 2023 Actual | G18: 2024 Actual | H18: 2025 Actual | I18: 2026 Forecast | J18: 2027 Forecast | K18: 2028 Forecast | L18: 2029 Forecast | M18: 2030 Forecast
A19: Price-earnings | B19: ='DCF Valuation'!$B$10/'Financial Statements'!C28 -> 53.014078 | C19: ='DCF Valuation'!$B$10/'Financial Statements'!D28 -> 43.222609 | D19: ='DCF Valuation'!$B$10/'Financial Statements'!E28 -> 40.59621 | E19: ='DCF Valuation'!$B$10/'Financial Statements'!F28 -> 33.896618 | F19: ='DCF Valuation'!$B$10/'Financial Statements'!G28 -> 39.905267 | G19: ='DCF Valuation'!$B$10/'Financial Statements'!H28 -> 24.606931 | H19: ='DCF Valuation'!$B$10/'Financial Statements'!I28 -> 19.458973 | I19: ='DCF Valuation'!$B$10/'Financial Statements'!J28 -> 66.84483 | ... M19: ='DCF Valuation'!$B$10/'Financial Statements'!N28 -> 39.575029
A20: Price-book | B20: ='DCF Valuation'!$B$10/('Financial Statements'!C38/'Financial Statements'!C36) -> 12.687984 | C20: ='DCF Valuation'!$B$10/('Financial Statements'!D38/'Financial Statements'!D36) -> 11.513979 | D20: ='DCF Valuation'!$B$10/('Financial Statements'!E38/'Financial Statements'!E36) -> 10.05778 | E20: ='DCF Valuation'!$B$10/('Financial Statements'!F38/'Financial Statements'!F36) -> 8.9063699 | F20: ='DCF Valuation'!$B$10/('Financial Statements'!G38/'Financial Statements'!G36) -> 8.1419051 | G20: ='DCF Valuation'!$B$10/('Financial Statements'!H38/'Financial Statements'!H36) -> 7.1727772 | H20: ='DCF Valuation'!$B$10/('Financial Statements'!I38/'Financial Statements'!I36) -> 6.2528841 | I20: ='DCF Valuation'!$B$10/('Financial Statements'!J38/'Financial Statements'!J36) -> 6.2770601 | ... M20: ='DCF Valuation'!$B$10/('Financial Statements'!N38/'Financial Statements'!N36) -> 6.6183656
A21: EV/EBITDA | B21: ='DCF Valuation'!$K$26/'Financial Statements'!C14 -> 25.712958 | C21: ='DCF Valuation'!$K$26/'Financial Statements'!D14 -> 24.051869 | D21: ='DCF Valuation'!$K$26/'Financial Statements'!E14 -> 27.960468 | E21: ='DCF Valuation'!$K$26/'Financial Statements'!F14 -> 103.72099 | F21: ='DCF Valuation'!$K$26/'Financial Statements'!G14 -> 24.604751 | G21: ='DCF Valuation'!$K$26/'Financial Statements'!H14 -> 13.184483 | H21: ='DCF Valuation'!$K$26/'Financial Statements'!I14 -> 9.9147101 | I21: ='DCF Valuation'!$K$26/'Financial Statements'!J14 -> 14.775496 | ... M21: ='DCF Valuation'!$K$26/'Financial Statements'!N14 -> 9.6361294
A22: EV/Sales | B22: ='DCF Valuation'!$K$23/'Financial Statements'!C7 -> 3.1659962 | C22: ='DCF Valuation'!$K$23/'Financial Statements'!D7 -> 3.094684 | D22: ='DCF Valuation'!$K$23/'Financial Statements'!E7 -> 3.4660775 | E22: ='DCF Valuation'!$K$23/'Financial Statements'!F7 -> 2.992415 | F22: ='DCF Valuation'!$K$23/'Financial Statements'!G7 -> 2.7309265 | G22: ='DCF Valuation'!$K$23/'Financial Statements'!H7 -> 2.3636579 | H22: ='DCF Valuation'!$K$23/'Financial Statements'!I7 -> 2.0570427 | I22: ='DCF Valuation'!$K$23/'Financial Statements'!J7 -> 1.9046691 | ... M22: ='DCF Valuation'!$K$23/'Financial Statements'!N7 -> 1.3999887
A23: Dividend payout ratio (%) | B23: ='Financial Statements'!C29/'Financial Statements'!C25 -> 0.0015886381 | C23: ='Financial Statements'!D29/'Financial Statements'!D25 -> 0.001725499 | D23: ='Financial Statements'!E29/'Financial Statements'!E25 -> 0.0020257021 | E23: ='Financial Statements'!F29/'Financial Statements'!F25 -> 0.0016903713 | F23: ='Financial Statements'!G29/'Financial Statements'!G25 -> 0.003381779 | G23: ='Financial Statements'!H29/'Financial Statements'!H25 -> 0.0031884236 | H23: ='Financial Statements'!I29/'Financial Statements'!I25 -> 0.003102188 | I23: ='Financial Statements'!J29/'Financial Statements'!J25 -> 0.013331391 | ... M23: ='Financial Statements'!N29/'Financial Statements'!N25 -> 0.014206968
A24: Dividend yield (%) | B24: =('Financial Statements'!C29/'Financial Statements'!C36)/'DCF Valuation'!$B$10 -> 1.4981975e-05 | C24: =('Financial Statements'!D29/'Financial Statements'!D36)/'DCF Valuation'!$B$10 -> 1.996234e-05 | D24: =('Financial Statements'!E29/'Financial Statements'!E36)/'DCF Valuation'!$B$10 -> 2.4946736e-05 | E24: =('Financial Statements'!F29/'Financial Statements'!F36)/'DCF Valuation'!$B$10 -> 2.4935914e-05 | F24: =('Financial Statements'!G29/'Financial Statements'!G36)/'DCF Valuation'!$B$10 -> 4.2372672e-05 | G24: =('Financial Statements'!H29/'Financial Statements'!H36)/'DCF Valuation'!$B$10 -> 6.478921e-05 | H24: =('Financial Statements'!I29/'Financial Statements'!I36)/'DCF Valuation'!$B$10 -> 7.9715881e-05 | I24: =('Financial Statements'!J29/'Financial Statements'!J36)/'DCF Valuation'!$B$10 -> 9.9614015e-05 | ... M24: =('Financial Statements'!N29/'Financial Statements'!N36)/'DCF Valuation'!$B$10 -> 0.00017908355
A26: B/S ratios | B26: 2019 Actual | C26: 2020 Actual | D26: 2021 Actual | E26: 2022 Actual | F26: 2023 Actual | G26: 2024 Actual | H26: 2025 Actual | I26: 2026 Forecast | J26: 2027 Forecast | K26: 2028 Forecast | L26: 2029 Forecast | M26: 2030 Forecast
A27: Inventory days | B27: ='IS ,BS Assumptions'!B46 -> 84.610377 | C27: ='IS ,BS Assumptions'!C46 -> 87.114569 | D27: ='IS ,BS Assumptions'!D46 -> 99.650495 | E27: ='IS ,BS Assumptions'!E46 -> 97.184621 | F27: ='IS ,BS Assumptions'!F46 -> 83.388501 | G27: ='IS ,BS Assumptions'!G46 -> 71.665731 | H27: ='IS ,BS Assumptions'!H46 -> 69.131487 | I27: ='IS ,BS Assumptions'!I46 -> 84 | ... M27: ='IS ,BS Assumptions'!M46 -> 76
A28: Creditor days | B28: ='IS ,BS Assumptions'!B50 -> 43.695839 | C28: ='IS ,BS Assumptions'!C50 -> 46.482094 | D28: ='IS ,BS Assumptions'!D50 -> 48.294068 | E28: ='IS ,BS Assumptions'!E50 -> 43.76418 | F28: ='IS ,BS Assumptions'!F50 -> 41.700357 | G28: ='IS ,BS Assumptions'!G50 -> 37.09913 | H28: ='IS ,BS Assumptions'!H50 -> 36.101841 | I28: ='IS ,BS Assumptions'!I50 -> 34 | ... M28: ='IS ,BS Assumptions'!M50 -> 35
A29: Debtor days | B29: ='IS ,BS Assumptions'!B48 -> 93.469009 | C29: ='IS ,BS Assumptions'!C48 -> 102.65291 | D29: ='IS ,BS Assumptions'!D48 -> 98.021629 | E29: ='IS ,BS Assumptions'!E48 -> 77.910293 | F29: ='IS ,BS Assumptions'!F48 -> 73.49417 | G29: ='IS ,BS Assumptions'!G48 -> 59.05748 | H29: ='IS ,BS Assumptions'!H48 -> 73.977813 | I29: ='IS ,BS Assumptions'!I48 -> 72 | ... M29: ='IS ,BS Assumptions'!M48 -> 65
A30: Asset turnover | B30: ='Financial Statements'!C7/'Financial Statements'!C70 -> 0.67181376 | C30: ='Financial Statements'!D7/'Financial Statements'!D70 -> 0.62037445 | D30: ='Financial Statements'!E7/'Financial Statements'!E70 -> 0.49219813 | E30: ='Financial Statements'!F7/'Financial Statements'!F70 -> 0.51443138 | F30: ='Financial Statements'!G7/'Financial Statements'!G70 -> 0.51982518 | G30: ='Financial Statements'!H7/'Financial Statements'!H70 -> 0.53373965 | H30: ='Financial Statements'!I7/'Financial Statements'!I70 -> 0.53548332 | I30: ='Financial Statements'!J7/'Financial Statements'!J70 -> 0.57103811 | ... M30: ='Financial Statements'!N7/'Financial Statements'!N70 -> 0.78779002
A31: Current ratio | B31: ='Financial Statements'!C68/'Financial Statements'!C50 -> 4.0026731 | C31: ='Financial Statements'!D68/'Financial Statements'!D50 -> 3.4463767 | D31: ='Financial Statements'!E68/'Financial Statements'!E50 -> 3.7861839 | E31: ='Financial Statements'!F68/'Financial Statements'!F50 -> 4.2623508 | F31: ='Financial Statements'!G68/'Financial Statements'!G50 -> 4.9527473 | G31: ='Financial Statements'!H68/'Financial Statements'!H50 -> 5.1909651 | H31: ='Financial Statements'!I68/'Financial Statements'!I50 -> 5.7702785 | I31: ='Financial Statements'!J68/'Financial Statements'!J50 -> 4.7884184 | ... M31: ='Financial Statements'!N68/'Financial Statements'!N50 -> 2.5095032
A32: Debt/equity | B32: =('Financial Statements'!C40+'Financial Statements'!C41)/'Financial Statements'!C38 -> 0 | C32: =('Financial Statements'!D40+'Financial Statements'!D41)/'Financial Statements'!D38 -> 0 | D32: =('Financial Statements'!E40+'Financial Statements'!E41)/'Financial Statements'!E38 -> 0.0014783546 | E32: =('Financial Statements'!F40+'Financial Statements'!F41)/'Financial Statements'!F38 -> 0.00068980681 | F32: =('Financial Statements'!G40+'Financial Statements'!G41)/'Financial Statements'!G38 -> 0.0014420761 | G32: =('Financial Statements'!H40+'Financial Statements'!H41)/'Financial Statements'!H38 -> 0.001056341 | H32: =('Financial Statements'!I40+'Financial Statements'!I41)/'Financial Statements'!I38 -> 0.0026847988 | I32: =('Financial Statements'!J40+'Financial Statements'!J41)/'Financial Statements'!J38 -> 0.0028290624 | ... M32: =('Financial Statements'!N40+'Financial Statements'!N41)/'Financial Statements'!N38 -> 0.0036212368
A33: Interest Coverage ratio | B33: ='Financial Statements'!C20/'Financial Statements'!C18 -> 56.649971 | C33: ='Financial Statements'!D20/'Financial Statements'!D18 -> 28.766436 | D33: ='Financial Statements'!E20/'Financial Statements'!E18 -> 20.842689 | E33: ='Financial Statements'!F20/'Financial Statements'!F18 -> -2.9873747 | F33: ='Financial Statements'!G20/'Financial Statements'!G18 -> 45.08846 | G33: ='Financial Statements'!H20/'Financial Statements'!H18 -> 118.43802 | H33: ='Financial Statements'!I20/'Financial Statements'!I18 -> 224.80543 | I33: ='Financial Statements'!J20/'Financial Statements'!J18 -> 108.88493 | ... M33: ='Financial Statements'!N20/'Financial Statements'!N18 -> 151.09982

Sheet Key Ratios Forecast
A1: KEY FORECAST
A3: INR Cr. | B3: 2025 Actual | C3: 2026 Forecast | D3: 2027 Forecast | E3: 2028 Forecast | F3: 2029 Forecast | G3: 2030 Forecast
A4: Operating Income | B4: ='Financial Statements'!I20 -> 3396.81 | C4: ='Financial Statements'!J20 -> 1959.9288 | D4: ='Financial Statements'!K20 -> 2182.4869 | E4: ='Financial Statements'!L20 -> 2394.5387 | F4: ='Financial Statements'!M20 -> 2682.8471 | G4: ='Financial Statements'!N20 -> 3324.1961
A5: EBIT Growth | B5: ='Financial Statements'!I21 -> 0.17835845 | C5: ='Financial Statements'!J21 -> 0.095288167 | D5: ='Financial Statements'!K21 -> 0.098248648 | E5: ='Financial Statements'!L21 -> 0.099809765 | F5: ='Financial Statements'!M21 -> 0.10354362 | G5: ='Financial Statements'!N21 -> 0.11879285
A6: EBITDA | B6: ='Financial Statements'!I14 -> 3970.7 | C6: ='Financial Statements'!J14 -> 2664.4344 | D6: ='Financial Statements'!K14 -> 2896.0178 | E6: ='Financial Statements'!L14 -> 3131.3698 | F6: ='Financial Statements'!M14 -> 3403.9056 | G6: ='Financial Statements'!N14 -> 4085.493
A7: EBITDA Margin (%) | B7: ='Financial Statements'!I15 -> 0.20849206 | C7: ='Financial Statements'!J15 -> 0.12953995 | D7: ='Financial Statements'!K15 -> 0.13036955 | E7: ='Financial Statements'!L15 -> 0.13052255 | F7: ='Financial Statements'!M15 -> 0.13137264 | G7: ='Financial Statements'!N15 -> 0.14599841
A8: Net Income | B8: ='Financial Statements'!I25 -> 5157.65 | C8: ='Financial Statements'!J25 -> 1500.2186 | D8: ='Financial Statements'!K25 -> 1673.3212 | E8: ='Financial Statements'!L25 -> 1821.2089 | F8: ='Financial Statements'!M25 -> 2043.3786 | G8: ='Financial Statements'!N25 -> 2533.9679
A9: EPS | B9: ='Financial Statements'!I28 -> 63.86 | C9: ='Financial Statements'!J28 -> 18.590069 | D9: ='Financial Statements'!K28 -> 20.735083 | E9: ='Financial Statements'!L28 -> 22.567645 | F9: ='Financial Statements'!M28 -> 25.320676 | G9: ='Financial Statements'!N28 -> 31.39985
A10: Dividend yield (%) | B10: ='Financial Statements'!I29/'Financial Statements'!I36 -> 0.09905894 | C10: ='Financial Statements'!J29/'Financial Statements'!J36 -> 0.12378536 | D10: ='Financial Statements'!K29/'Financial Statements'!K36 -> 0.14849647 | E10: ='Financial Statements'!L29/'Financial Statements'!L36 -> 0.17319231 | F10: ='Financial Statements'!M29/'Financial Statements'!M36 -> 0.19787287 | G10: ='Financial Statements'!N29/'Financial Statements'!N36 -> 0.22253817
A11: ROCE (%) | B11: ='All Ratios Forecast'!H16 -> 0.096274204 | C11: ='All Ratios Forecast'!I16 -> 0.054865899 | D11: ='All Ratios Forecast'!J16 -> 0.061099977 | E11: ='All Ratios Forecast'!K16 -> 0.067388467 | F11: ='All Ratios Forecast'!L16 -> 0.076137326 | G11: ='All Ratios Forecast'!M16 -> 0.094545388
A12: ROE (%) | B12: ='All Ratios Forecast'!H15 -> 0.16067826 | C12: ='All Ratios Forecast'!I15 -> 0.04690307 | D12: ='All Ratios Forecast'!J15 -> 0.052749417 | E12: ='All Ratios Forecast'!K15 -> 0.058215834 | F12: ='All Ratios Forecast'!L15 -> 0.066462645 | G12: ='All Ratios Forecast'!M15 -> 0.083426698
A13: PE | B13: ='All Ratios Forecast'!H19 -> 19.458973 | C13: ='All Ratios Forecast'!I19 -> 66.84483 | D13: ='All Ratios Forecast'!J19 -> 59.929829 | E13: ='All Ratios Forecast'!K19 -> 55.063344 | F13: ='All Ratios Forecast'!L19 -> 49.076494 | G13: ='All Ratios Forecast'!M19 -> 39.575029
A14: P/BV | B14: ='All Ratios Forecast'!H20 -> 6.2528841 | C14: ='All Ratios Forecast'!I20 -> 6.2770601 | D14: ='All Ratios Forecast'!J20 -> 6.3311452 | E14: ='All Ratios Forecast'!K20 -> 6.4218419 | F14: ='All Ratios Forecast'!L20 -> 6.536441 | G14: ='All Ratios Forecast'!M20 -> 6.6183656

Sheet Peer master data
A1: Peer Comparison
A2: Company Name | B2: Year | C2: Revenue Growth | D2: EBITDA Margin | E2: Return on Assets | F2: Return on Equity | G2: Current Ratio | H2: Debt/Equity Ratio | I2: Interest Coverage Ratio | J2: Asset Turnover
A3: Sun pharma | B3: 2019 | C3: N/A | D3: 0.28 | E3: 0.086 | F3: 0.095 | G3: 1.71 | H3: 0.06 | I3: 10.1 | J3: 0.38
A4: Sun pharma | B4: 2020 | C4: 0.097 | D4: 0.273 | E4: 0.064 | F4: 0.072 | G4: 1.65 | H4: 0.05 | I4: 11.4 | J4: 0.4
A5: Sun pharma | B5: 2021 | C5: 0.025 | D5: 0.27 | E5: 0.069 | F5: 0.078 | G5: 1.72 | H5: 0.04 | I5: 12.8 | J5: 0.38
A6: Sun pharma | B6: 2022 | C6: 0.168 | D6: 0.281 | E6: 0.092 | F6: 0.104 | G6: 1.88 | H6: 0.03 | I6: 16.2 | J6: 0.42
A7: Sun pharma | B7: 2023 | C7: 0.118 | D7: 0.285 | E7: 0.107 | F7: 0.118 | G7: 1.96 | H7: 0.02 | I7: 21.3 | J7: 0.44
A8: Sun pharma | B8: 2024 | C8: 0.135 | D8: 0.298 | E8: 0.121 | F8: 0.152 | G8: 2.1 | H8: 0.01 | I8: 28.4 | J8: 0.46
A9: Sun pharma | B9: 2025 | C9: 0.132 | D9: 0.309 | E9: 0.128 | F9: 0.152 | G9: 2.18 | H9: 0 | I9: 35.1 | J9: 0.48
A10: Zydus | B10: 2019 | C10: N/A | D10: 0.211 | E10: 0.091 | F10: 0.149 | G10: 2.1 | H10: 0.22 | I10: 8.4 | J10: 0.68
A11: Zydus | B11: 2020 | C11: 0.073 | D11: 0.202 | E11: 0.086 | F11: 0.14 | G11: 2.05 | H11: 0.2 | I11: 9.1 | J11: 0.65
A12: Zydus | B12: 2021 | C12: 0.014 | D12: 0.228 | E12: 0.088 | F12: 0.14 | G12: 2.18 | H12: 0.17 | I12: 10.2 | J12: 0.62
A13: Zydus | B13: 2022 | C13: 0.048 | D13: 0.221 | E13: 0.095 | F13: 0.15 | G13: 2.26 | H13: 0.14 | I13: 12.5 | J13: 0.64
A14: Zydus | B14: 2023 | C14: 0.176 | D14: 0.245 | E14: 0.118 | F14: 0.178 | G14: 2.33 | H14: 0.09 | I14: 17.8 | J14: 0.72
A15: Zydus | B15: 2024 | C15: 0.193 | D15: 0.261 | E15: 0.147 | F15: 0.209 | G15: 2.51 | H15: 0.06 | I15: 22.4 | J15: 0.78
A16: Zydus | B16: 2025 | C16: 0.118 | D16: 0.275 | E16: 0.161 | F16: 0.225 | G16: 2.62 | H16: 0.04 | I16: 28.6 | J16: 0.82
A17: Dr. Reddy | B17: 2019 | C17: N/A | D17: 0.185 | E17: 0.074 | F17: 0.112 | G17: 2.08 | H17: 0.28 | I17: 7.8 | J17: 0.56
A18: Dr. Reddy | B18: 2020 | C18: 0.151 | D18: 0.226 | E18: 0.088 | F18: 0.132 | G18: 2.15 | H18: 0.22 | I18: 9.6 | J18: 0.6
A19: Dr. Reddy | B19: 2021 | C19: 0.11 | D19: 0.238 | E19: 0.101 | F19: 0.148 | G19: 2.22 | H19: 0.16 | I19: 11.4 | J19: 0.62
A20: Dr. Reddy | B20: 2022 | C20: 0.159 | D20: 0.249 | E20: 0.118 | F20: 0.166 | G20: 2.38 | H20: 0.12 | I20: 14.2 | J20: 0.65
A21: Dr. Reddy | B21: 2023 | C21: 0.126 | D21: 0.261 | E21: 0.148 | F21: 0.195 | G21: 2.44 | H21: 0.08 | I21: 18.5 | J21: 0.7
A22: Dr. Reddy | B22: 2024 | C22: 0.168 | D22: 0.271 | E22: 0.172 | F22: 0.214 | G22: 2.52 | H22: 0.05 | I22: 25.1 | J22: 0.74
A23: Dr. Reddy | B23: 2025 | C23: 0.12 | D23: 0.282 | E23: 0.188 | F23: 0.214 | G23: 2.61 | H23: 0.04 | I23: 31.4 | J23: 0.77
A24: Lupin | B24: 2019 | C24: N/A | D24: 0.174 | E24: 0.069 | F24: 0.125 | G24: 2.02 | H24: 0.41 | I24: 5.8 | J24: 0.58
A25: Lupin | B25: 2020 | C25: 0.047 | D25: 0.187 | E25: 0.052 | F25: 0.092 | G25: 1.95 | H25: 0.38 | I25: 6.2 | J25: 0.57
A26: Lupin | B26: 2021 | C26: -0.097 | D26: 0.192 | E26: 0.048 | F26: 0.086 | G26: 2.05 | H26: 0.32 | I26: 7.4 | J26: 0.52
A27: Lupin | B27: 2022 | C27: 0.025 | D27: 0.181 | E27: 0.058 | F27: 0.101 | G27: 2.1 | H27: 0.26 | I27: 8.8 | J27: 0.55
A28: Lupin | B28: 2023 | C28: 0.144 | D28: 0.196 | E28: 0.078 | F28: 0.135 | G28: 2.25 | H28: 0.18 | I28: 12.5 | J28: 0.59
A29: Lupin | B29: 2024 | C29: 0.175 | D29: 0.218 | E29: 0.098 | F29: 0.168 | G29: 2.38 | H29: 0.12 | I29: 17.8 | J29: 0.64
A30: Lupin | B30: 2025 | C30: 0.136 | D30: 0.247 | E30: 0.132 | F30: 0.209 | G30: 2.52 | H30: 0.06 | I30: 24.3 | J30: 0.7

Sheet Dashboard Peer Comparison
A4: Average of Revenue Growth | B4: Column Labels | H4: Sum of EBITDA Margin | I4: Column Labels | R4: Sum of Return on Assets | S4: Column Labels
A5: Row Labels | B5: Dr. Reddy | C5: Lupin | D5: Sun pharma | E5: Zydus | F5: Grand Total | H5: Row Labels | I5: Dr. Reddy | J5: Lupin | K5: Sun pharma | L5: Zydus | M5: Grand Total | R5: Row Labels | S5: Dr. Reddy | T5: Lupin | U5: Sun pharma | V5: Zydus | W5: Grand Total
A6: 2019 | B6: #DIV/0! | C6: #DIV/0! | D6: #DIV/0! | E6: #DIV/0! | F6: #DIV/0! | H6: 2019 | I6: 0.185 | J6: 0.174 | K6: 0.28 | L6: 0.211 | M6: 0.85 | R6: 2019 | S6: 0.074 | T6: 0.069 | U6: 0.086 | V6: 0.091 | W6: 0.32
A7: 2020 | B7: 0.151 | C7: 0.047 | D7: 0.097 | E7: 0.073 | F7: 0.092 | H7: 2020 | I7: 0.226 | J7: 0.187 | K7: 0.273 | L7: 0.202 | M7: 0.888 | R7: 2020 | S7: 0.088 | T7: 0.052 | U7: 0.064 | V7: 0.086 | W7: 0.29
A8: 2021 | B8: 0.11 | C8: -0.097 | D8: 0.025 | E8: 0.014 | F8: 0.013 | H8: 2021 | I8: 0.238 | J8: 0.192 | K8: 0.27 | L8: 0.228 | M8: 0.928 | R8: 2021 | S8: 0.101 | T8: 0.048 | U8: 0.069 | V8: 0.088 | W8: 0.306
A9: 2022 | B9: 0.159 | C9: 0.025 | D9: 0.168 | E9: 0.048 | F9: 0.1 | H9: 2022 | I9: 0.249 | J9: 0.181 | K9: 0.281 | L9: 0.221 | M9: 0.932 | R9: 2022 | S9: 0.118 | T9: 0.058 | U9: 0.092 | V9: 0.095 | W9: 0.363
A10: 2023 | B10: 0.126 | C10: 0.144 | D10: 0.118 | E10: 0.176 | F10: 0.141 | H10: 2023 | I10: 0.261 | J10: 0.196 | K10: 0.285 | L10: 0.245 | M10: 0.987 | R10: 2023 | S10: 0.148 | T10: 0.078 | U10: 0.107 | V10: 0.118 | W10: 0.451
A11: 2024 | B11: 0.168 | C11: 0.175 | D11: 0.135 | E11: 0.193 | F11: 0.16775 | H11: 2024 | I11: 0.271 | J11: 0.218 | K11: 0.298 | L11: 0.261 | M11: 1.048 | R11: 2024 | S11: 0.172 | T11: 0.098 | U11: 0.121 | V11: 0.147 | W11: 0.538
A12: 2025 | B12: 0.12 | C12: 0.136 | D12: 0.132 | E12: 0.118 | F12: 0.1265 | H12: 2025 | I12: 0.282 | J12: 0.247 | K12: 0.309 | L12: 0.275 | M12: 1.113 | R12: 2025 | S12: 0.188 | T12: 0.132 | U12: 0.128 | V12: 0.161 | W12: 0.609
A13: Grand Total | B13: 0.139 | C13: 0.071666667 | D13: 0.1125 | E13: 0.10366667 | F13: 0.10670833 | H13: Grand Total | I13: 1.712 | J13: 1.395 | K13: 1.996 | L13: 1.643 | M13: 6.746 | R13: Grand Total | S13: 0.889 | T13: 0.535 | U13: 0.667 | V13: 0.786 | W13: 2.877
A16: Sum of Return on Equity | B16: Column Labels | H16: Sum of Current Ratio | I16: Column Labels | R16: Sum of Debt/Equity Ratio | S16: Column Labels
A17: Row Labels | B17: Dr. Reddy | C17: Lupin | D17: Sun pharma | E17: Zydus | F17: Grand Total | H17: Row Labels | I17: Dr. Reddy | J17: Lupin | K17: Sun pharma | L17: Zydus | M17: Grand Total | R17: Row Labels | S17: Dr. Reddy | T17: Lupin | U17: Sun pharma | V17: Zydus | W17: Grand Total
A18: 2019 | B18: 0.112 | C18: 0.125 | D18: 0.095 | E18: 0.149 | F18: 0.481 | H18: 2019 | I18: 2.08 | J18: 2.02 | K18: 1.71 | L18: 2.1 | M18: 7.91 | R18: 2019 | S18: 0.28 | T18: 0.41 | U18: 0.06 | V18: 0.22 | W18: 0.97
A19: 2020 | B19: 0.132 | C19: 0.092 | D19: 0.072 | E19: 0.14 | F19: 0.436 | H19: 2020 | I19: 2.15 | J19: 1.95 | K19: 1.65 | L19: 2.05 | M19: 7.8 | R19: 2020 | S19: 0.22 | T19: 0.38 | U19: 0.05 | V19: 0.2 | W19: 0.85
A20: 2021 | B20: 0.148 | C20: 0.086 | D20: 0.078 | E20: 0.14 | F20: 0.452 | H20: 2021 | I20: 2.22 | J20: 2.05 | K20: 1.72 | L20: 2.18 | M20: 8.17 | R20: 2021 | S20: 0.16 | T20: 0.32 | U20: 0.04 | V20: 0.17 | W20: 0.69
A21: 2022 | B21: 0.166 | C21: 0.101 | D21: 0.104 | E21: 0.15 | F21: 0.521 | H21: 2022 | I21: 2.38 | J21: 2.1 | K21: 1.88 | L21: 2.26 | M21: 8.62 | R21: 2022 | S21: 0.12 | T21: 0.26 | U21: 0.03 | V21: 0.14 | W21: 0.55
A22: 2023 | B22: 0.195 | C22: 0.135 | D22: 0.118 | E22: 0.178 | F22: 0.626 | H22: 2023 | I22: 2.44 | J22: 2.25 | K22: 1.96 | L22: 2.33 | M22: 8.98 | R22: 2023 | S22: 0.08 | T22: 0.18 | U22: 0.02 | V22: 0.09 | W22: 0.37
A23: 2024 | B23: 0.214 | C23: 0.168 | D23: 0.152 | E23: 0.209 | F23: 0.743 | H23: 2024 | I23: 2.52 | J23: 2.38 | K23: 2.1 | L23: 2.51 | M23: 9.51 | R23: 2024 | S23: 0.05 | T23: 0.12 | U23: 0.01 | V23: 0.06 | W23: 0.24
A24: 2025 | B24: 0.214 | C24: 0.209 | D24: 0.152 | E24: 0.225 | F24: 0.8 | H24: 2025 | I24: 2.61 | J24: 2.52 | K24: 2.18 | L24: 2.62 | M24: 9.93 | R24: 2025 | S24: 0.04 | T24: 0.06 | U24: 0 | V24: 0.04 | W24: 0.14
A25: Grand Total | B25: 1.181 | C25: 0.916 | D25: 0.771 | E25: 1.191 | F25: 4.059 | H25: Grand Total | I25: 16.4 | J25: 15.27 | K25: 13.2 | L25: 16.05 | M25: 60.92 | R25: Grand Total | S25: 0.95 | T25: 1.73 | U25: 0.21 | V25: 0.92 | W25: 3.81
A28: Sum of Interest Coverage Ratio | B28: Column Labels
A29: Row Labels | B29: Dr. Reddy | C29: Lupin | D29: Sun pharma | E29: Zydus | F29: Grand Total | H29: Sum of Asset Turnover | I29: Column Labels
A30: 2019 | B30: 7.8 | C30: 5.8 | D30: 10.1 | E30: 8.4 | F30: 32.1 | H30: Row Labels | I30: Dr. Reddy | J30: Lupin | K30: Sun pharma | L30: Zydus | M30: Grand Total
A31: 2020 | B31: 9.6 | C31: 6.2 | D31: 11.4 | E31: 9.1 | F31: 36.3 | H31: 2019 | I31: 0.56 | J31: 0.58 | K31: 0.38 | L31: 0.68 | M31: 2.2
A32: 2021 | B32: 11.4 | C32: 7.4 | D32: 12.8 | E32: 10.2 | F32: 41.8 | H32: 2020 | I32: 0.6 | J32: 0.57 | K32: 0.4 | L32: 0.65 | M32: 2.22
A33: 2022 | B33: 14.2 | C33: 8.8 | D33: 16.2 | E33: 12.5 | F33: 51.7 | H33: 2021 | I33: 0.62 | J33: 0.52 | K33: 0.38 | L33: 0.62 | M33: 2.14
A34: 2023 | B34: 18.5 | C34: 12.5 | D34: 21.3 | E34: 17.8 | F34: 70.1 | H34: 2022 | I34: 0.65 | J34: 0.55 | K34: 0.42 | L34: 0.64 | M34: 2.26
A35: 2024 | B35: 25.1 | C35: 17.8 | D35: 28.4 | E35: 22.4 | F35: 93.7 | H35: 2023 | I35: 0.7 | J35: 0.59 | K35: 0.44 | L35: 0.72 | M35: 2.45
A36: 2025 | B36: 31.4 | C36: 24.3 | D36: 35.1 | E36: 28.6 | F36: 119.4 | H36: 2024 | I36: 0.74 | J36: 0.64 | K36: 0.46 | L36: 0.78 | M36: 2.62
A37: Grand Total | B37: 118 | C37: 82.8 | D37: 135.3 | E37: 109 | F37: 445.1 | H37: 2025 | I37: 0.77 | J37: 0.7 | K37: 0.48 | L37: 0.82 | M37: 2.77
H38: Grand Total | I38: 4.64 | J38: 4.15 | K38: 2.96 | L38: 4.91 | M38: 16.66

Sheet DashBoard Peer Company
A1: PHARMA INDUSTRY- PEER COMPARISON
